src/shared_memory.v
`define BYTE 8
`define NUM_SLAVE 4
`define MAX_STRING 32
  `define MAX_STR_ADD 5
`define MAX_PATTERN 8
  `define MAX_PAT_ADD 3

module shared_memory(clk, reset, w_data, write, w_sel, str_reg, pat_reg);
  input clk;
  input reset;
  input [`BYTE - 1:0] w_data;
  input write;
  input w_sel;

  output reg [`MAX_STRING * `BYTE - 1 : 0] str_reg;
  output reg [`MAX_PATTERN * `BYTE - 1 : 0] pat_reg;
//---------------------input/output---------------------

  integer i, j;
  parameter sel_str_reg = 0;
  parameter sel_pat_reg = 1;

  reg [`MAX_STR_ADD - 1 : 0] s_index;
  reg [`MAX_PAT_ADD - 1 : 0] p_index;


  always@(posedge clk)
  begin
      if(reset)
      begin
        s_index <= 0;
        p_index <= 0;

        for(i = 0; i < (`MAX_STRING * `BYTE); i = i + 1)
        begin
          str_reg[i] <= 0;
        end

        for(j = 0; j < (`MAX_PATTERN * `BYTE); j = j + 1)
        begin
          pat_reg[j] <= 0;
        end
      end
      
      else if(write)
      begin
        case(w_sel)
          sel_str_reg : begin str_reg[s_index * `BYTE +: `BYTE] <= w_data; s_index <= s_index + 1; end
          sel_pat_reg : begin pat_reg[p_index * `BYTE +: `BYTE] <= w_data; p_index <= p_index + 1; end
        endcase
      end

      else
      begin
        s_index <= 0;
        p_index <= 0;
      end
end

endmodule

src/SME.v
module SME(
  input clk,
  input reset,
  input [7:0] chardata,
  input isstring,
  input ispattern,
  output reg valid,
  output reg match,
  output reg [4:0] match_index
  );

  wire write;
  assign write = (ispattern || isstring)? 1:0;
  wire w_sel;
  assign w_sel = (ispattern)? 1:0;

  wire [255:0]str;
  wire [63:0] pat;
  shared_memory s1(.clk(clk), .reset(reset), .w_data(chardata), .write(write), .w_sel(w_sel), .str_reg(str), .pat_reg(pat));



endmodule

test_bench/sme_tb_term.sv
`timescale 1ns/10ps
`define CYCLE      1.0
`define SDFFILE    "./SME_syn.sdf"
`define End_CYCLE  1000000
`define PAT        "./Btestdata.txt"
module testfixture();

integer linedata;
integer char_count;
//reg [128:0] data;
string data;
string strnum;
string patnum;
string strdata;
string goldmatch_s;
string goldmatch_index_s;

reg clk = 0;
wire valid;
reg reset =0;
reg [7:0] chardata;
reg isstring=0;
reg ispattern=0;
wire match;
wire [4:0] match_index;
SME u_SME (.clk(clk),
           .reset(reset),
           .chardata(chardata),
           .isstring(isstring),
           .ispattern(ispattern),
           .valid(valid),
           .match(match),
           .match_index(match_index));

`ifdef SDF
    initial $sdf_annotate(`SDFFILE, u_SME);
`endif

always begin #(`CYCLE/2) clk = ~clk; end

/*
initial begin
    $fsdbDumpfile("SME.fsdb");
    $fsdbDumpvars;
    $fsdbDumpMDA;
end
*/

initial begin
    $dumpfile("SME.vcd");
    $dumpvars;
end

initial begin
    $display("----------------------");
    $display("-- Simulation Start --");
    $display("----------------------");
    @(posedge clk); #1; reset = 1'b1; 
    #(`CYCLE*2);  
    @(posedge clk); #1;   reset = 1'b0;
end

reg [22:0] cycle=0;

always @(posedge clk) begin
    cycle=cycle+1;
    if (cycle > `End_CYCLE) begin
        $display("--------------------------------------------------");
        $display("-- Failed waiting valid signal, Simulation STOP --");
        $display("--------------------------------------------------");
        $fclose(linedata);
        $finish;
    end
end

initial begin
    linedata = $fopen(`PAT,"r");
    if (linedata == 0) begin
        $display ("pattern handle null");
        $finish;
    end
end

integer strindex;
reg [7:0] goldmatch_index;
reg  goldmatch;
reg  valid_reg;
reg wait_valid;
reg  getmatch;
reg [7:0] getmatch_index;
always @(posedge clk) begin
    valid_reg = valid;
end

integer score=0;
integer allpass=1;
always @(negedge clk) begin
    if (reset) begin
        wait_valid=0;
    end
    else begin
        if (wait_valid==1 && valid ==1) begin
            wait_valid=0;
            getmatch=match;
            getmatch_index=match_index;
            //$display ("       string/pattern = %s/%s",strnum,patnum);
            if(goldmatch==1)begin
                if(getmatch == goldmatch) begin
                    score++;
                    if(getmatch_index==goldmatch_index) begin
                        score=score+2;
                        colordisplay(cycle,goldmatch,goldmatch_index,getmatch,getmatch_index,3);
                        //$display ("       cycle %2h, expect(%h,%h) , get(%h,%h) >> Pass",cycle,goldmatch,goldmatch_index,getmatch,getmatch_index);
                    end
                    else begin 
                        allpass=0;
                        colordisplay(cycle,goldmatch,goldmatch_index,getmatch,getmatch_index,2);
                        //$display ("       cycle %2h, expect(%h,%h) , get(%h,%h) >> Wrong index",cycle,goldmatch,goldmatch_index,getmatch,getmatch_index);
                    end
                end
                else begin
                    allpass=0;
                    colordisplay(cycle,goldmatch,goldmatch_index,getmatch,getmatch_index,0);
                    //$display ("       cycle %2h, expect(%h,%h) , get(%h,%h) >> Fail",cycle,goldmatch,goldmatch_index,getmatch,getmatch_index);
                end
            end
            else begin
                if(getmatch == goldmatch) begin
                    score++;
                    colordisplay(cycle,goldmatch,goldmatch_index,getmatch,getmatch_index,3);
                    //$display ("       cycle %2h, expect(%h,--) , get(%h,--) >> Pass",cycle, goldmatch,getmatch);
                end
                else begin
                    allpass=0;
                    colordisplay(cycle,goldmatch,goldmatch_index,getmatch,getmatch_index,1);
                    //$display ("       cycle %2h, expect(%h,--) , get(%h,--) >> Fail",cycle, goldmatch,getmatch);
                end
            end
        //$display ("       score = %d",score);
        end
    end
end

always @(negedge clk ) begin
    if (reset) begin
        isstring=0;
        ispattern=0;
        valid_reg=0;
    end 
    else begin
        if (strindex==strdata.len()-1) begin
            isstring=0;
            if(ispattern==1) wait_valid=1;
            ispattern=0;
        end
        if (wait_valid == 1'b0) begin
            if (strindex<strdata.len()-1) begin
                strindex=strindex+1;
                chardata = strdata.getc(strindex);
                //$display("%h %s,%h",cycle,chardata,chardata);
            end 
            else begin
                if (!$feof(linedata))begin
                    char_count = $fgets (data, linedata);
                    if (char_count !== 0) begin
                        if(data.substr(0,3) == "str:") begin
                            isstring=1; 
                            strindex=0;
                            strnum = data.substr(4,4);
                            strdata = data.substr(6,data.len()-2);
                            $display("  __________________________________________________________");
                            $display("  == String %s  \"%s\"", strnum, strdata);
                            chardata = strdata.getc(strindex);
                            //$display("%h %s,%h",cycle,chardata,chardata);
                        end 
                        else begin
                            if(data.substr(0,3) == "pat:") begin
                                ispattern=1; 
                                strindex=0;
                                patnum = data.substr(4,4);
                                goldmatch_s = data.substr(6,6);
                                goldmatch = goldmatch_s.atoi();
                                goldmatch_index_s = data.substr(8,9);
                                goldmatch_index = goldmatch_index_s.atoi();
                                strdata = data.substr(11,data.len()-2);
                                //$display("==== Pattern__%s__%b__%2d__%s", patnum, goldmatch,goldmatch_index,strdata);
                                $display("  -- Pattern %s  \"%s\"", patnum, strdata);
                                chardata = strdata.getc(strindex);
                                //$display("%h %s,%h",cycle,chardata,chardata);
                            end
                        end
                    end
                end
                else begin
                    $display("----------------------------------");
                    if(allpass == 1 && score >1)
                    $display("-- Simulation finish, ALL PASS  --");
                    else
                    $display("-- Simulation finish            --");
                    $display("-- cycle =%3d , Score =%2d       --",cycle, score);
                    $display("----------------------------------");
                    $fclose(linedata);
                    $finish;
                end
            end
        end // if wait_valid == 0
    end
end
endmodule

task colordisplay;
    input [12:0] cycle;
    input goldmatch;
    input [7:0] goldmatchindex;
    input getmatch;
    input [7:0] getmatchindex;
    input [1:0]pass; 
    begin
        $write ("       cycle %2h, expect(%h,%h) , get(",cycle,goldmatch,goldmatchindex);
        case(pass)
            2'd0: begin   // expect match , failed
                $write("%c[1;31m",27);
                $write ("%h,%h",getmatch,getmatchindex);
                $write("%c[0m",27);
                $write (") >> Fail\n");

                  end
            2'd1: begin   // expect unmatch, failed
                $write("%c[1;31m",27);
                $write ("%h",getmatch);
                $write ("%c[0m",27);
                $write (",%h) >> Fail\n",getmatchindex);

                  end
            2'd2: begin  // expect match, wrong index
                $write ("%h,",getmatch);
                $write("%c[1;31m",27);
                $write ("%h",getmatchindex);
                $write("%c[0m",27);
                $write (") >> Wrong index\n");

                  end
            2'd3: begin // both match or unmatch, passed
                $write ("%h,%h",getmatch,getmatchindex);
                $write (") >> Pass\n");

                  end
        endcase
    end
endtask

vivado_project/SME_parallel.sim/sim_1/behav/xsim/SME.vcd
$date
   Thu Dec  3 21:09:01 2020
$end
$version
  2019.1
$end
$timescale
  1ps
$end
$scope module testfixture $end
$var integer 32 ! linedata $end
$var integer 32 " char_count $end
$var reg 32 # data $end
$var reg 32 $ strnum $end
$var reg 32 % patnum $end
$var reg 32 & strdata $end
$var reg 32 ' goldmatch_s $end
$var reg 32 ( goldmatch_index_s $end
$var reg 1 ) clk $end
$var wire 1 * valid $end
$var reg 1 + reset $end
$var reg 8 , chardata [7:0] $end
$var reg 1 - isstring $end
$var reg 1 . ispattern $end
$var wire 1 / match $end
$var wire 5 0 match_index [4:0] $end
$var reg 23 1 cycle [22:0] $end
$var integer 32 2 strindex $end
$var reg 8 3 goldmatch_index [7:0] $end
$var reg 1 4 goldmatch $end
$var reg 1 5 valid_reg $end
$var reg 1 6 wait_valid $end
$var reg 1 7 getmatch $end
$var reg 8 8 getmatch_index [7:0] $end
$var integer 32 9 score $end
$var integer 32 : allpass $end
$scope module u_SME $end
$var wire 1 ; clk $end
$var wire 1 < reset $end
$var wire 8 = chardata [7:0] $end
$var wire 1 > isstring $end
$var wire 1 ? ispattern $end
$var reg 1 @ valid $end
$var reg 1 A match $end
$var reg 5 B match_index [4:0] $end
$var wire 1 C write $end
$var wire 1 D w_sel $end
$var wire 256 E str [255:0] $end
$var wire 64 F pat [63:0] $end
$scope module s1 $end
$var wire 1 ; clk $end
$var wire 1 < reset $end
$var wire 8 = w_data [7:0] $end
$var wire 1 C write $end
$var wire 1 D w_sel $end
$var reg 256 G str_reg [255:0] $end
$var reg 64 H pat_reg [63:0] $end
$var integer 32 I i $end
$var integer 32 J j $end
$var reg 5 K s_index [4:0] $end
$var reg 3 L p_index [2:0] $end
$var parameter 32 M sel_str_reg [31:0] $end
$var parameter 32 N sel_pat_reg [31:0] $end
$upscope $end
$upscope $end
$upscope $end
$enddefinitions $end
#0
$dumpvars
b11111111111111111011000111100000 !
bx "
b0 #
b0 $
b0 %
b0 &
b0 '
b0 (
0)
x*
0+
bx ,
0-
0.
x/
bx 0
b0 1
bx 2
bx 3
x4
x5
x6
x7
bx 8
b0 9
b1 :
0;
0<
bx =
0>
0?
x@
xA
bx B
0C
0D
bx E
bx F
bx G
bx H
bx I
bx J
bx K
bx L
b0 M
b1 N
$end
#500
1)
b1 1
1;
b0 K
b0 L
#1000
0)
0;
#1500
1)
1+
b10 1
1;
1<
b0 E
b0 F
b0 G
b0 H
b100000000 I
b1000000 J
b0 K
b0 L
#2000
0)
05
06
0;
#2500
1)
b11 1
x5
1;
b0 G
b0 H
b100000000 I
b1000000 J
b0 K
b0 L
#3000
0)
05
0;
#3500
1)
b100 1
x5
1;
b0 G
b0 H
b100000000 I
b1000000 J
b0 K
b0 L
#4000
0)
05
0;
#4500
1)
0+
b101 1
x5
1;
0<
b0 K
b0 L
#5000
b11100 "
0)
b1100001 ,
1-
b0 2
0;
b1100001 =
1>
1C
#5500
1)
b110 1
1;
b1100001 E
b1100001 G
b1 K
#6000
0)
b1100010 ,
b1 2
0;
b1100010 =
#6500
1)
b111 1
1;
b110001001100001 E
b110001001100001 G
b10 K
#7000
0)
b1100011 ,
b10 2
0;
b1100011 =
#7500
1)
b1000 1
1;
b11000110110001001100001 E
b11000110110001001100001 G
b11 K
#8000
0)
b1100100 ,
b11 2
0;
b1100100 =
#8500
1)
b1001 1
1;
b1100100011000110110001001100001 E
b1100100011000110110001001100001 G
b100 K
#9000
0)
b1101001 ,
b100 2
0;
b1101001 =
#9500
1)
b1010 1
1;
b110100101100100011000110110001001100001 E
b110100101100100011000110110001001100001 G
b101 K
#10000
0)
b1101010 ,
b101 2
0;
b1101010 =
#10500
1)
b1011 1
1;
b11010100110100101100100011000110110001001100001 E
b11010100110100101100100011000110110001001100001 G
b110 K
#11000
0)
b1101011 ,
b110 2
0;
b1101011 =
#11500
1)
b1100 1
1;
b1101011011010100110100101100100011000110110001001100001 E
b1101011011010100110100101100100011000110110001001100001 G
b111 K
#12000
0)
b100000 ,
b111 2
0;
b100000 =
#12500
1)
b1101 1
1;
b10000001101011011010100110100101100100011000110110001001100001 E
b10000001101011011010100110100101100100011000110110001001100001 G
b1000 K
#13000
0)
b1101100 ,
b1000 2
0;
b1101100 =
#13500
1)
b1110 1
1;
b11011000010000001101011011010100110100101100100011000110110001001100001 E
b11011000010000001101011011010100110100101100100011000110110001001100001 G
b1001 K
#14000
0)
b1101101 ,
b1001 2
0;
b1101101 =
#14500
1)
b1111 1
1;
b1101101011011000010000001101011011010100110100101100100011000110110001001100001 E
b1101101011011000010000001101011011010100110100101100100011000110110001001100001 G
b1010 K
#15000
0)
b1101110 ,
b1010 2
0;
b1101110 =
#15500
1)
b10000 1
1;
b110111001101101011011000010000001101011011010100110100101100100011000110110001001100001 E
b110111001101101011011000010000001101011011010100110100101100100011000110110001001100001 G
b1011 K
#16000
0)
b1101111 ,
b1011 2
0;
b1101111 =
#16500
1)
b10001 1
1;
b11011110110111001101101011011000010000001101011011010100110100101100100011000110110001001100001 E
b11011110110111001101101011011000010000001101011011010100110100101100100011000110110001001100001 G
b1100 K
#17000
0)
b1110000 ,
b1100 2
0;
b1110000 =
#17500
1)
b10010 1
1;
b1110000011011110110111001101101011011000010000001101011011010100110100101100100011000110110001001100001 E
b1110000011011110110111001101101011011000010000001101011011010100110100101100100011000110110001001100001 G
b1101 K
#18000
0)
b100000 ,
b1101 2
0;
b100000 =
#18500
1)
b10011 1
1;
b10000001110000011011110110111001101101011011000010000001101011011010100110100101100100011000110110001001100001 E
b10000001110000011011110110111001101101011011000010000001101011011010100110100101100100011000110110001001100001 G
b1110 K
#19000
0)
b1110001 ,
b1110 2
0;
b1110001 =
#19500
1)
b10100 1
1;
b11100010010000001110000011011110110111001101101011011000010000001101011011010100110100101100100011000110110001001100001 E
b11100010010000001110000011011110110111001101101011011000010000001101011011010100110100101100100011000110110001001100001 G
b1111 K
#20000
0)
b100000 ,
b1111 2
0;
b100000 =
#20500
1)
b10101 1
1;
b100000011100010010000001110000011011110110111001101101011011000010000001101011011010100110100101100100011000110110001001100001 E
b100000011100010010000001110000011011110110111001101101011011000010000001101011011010100110100101100100011000110110001001100001 G
b10000 K
#21000
0)
b1110010 ,
b10000 2
0;
b1110010 =
#21500
1)
b10110 1
1;
b111001000100000011100010010000001110000011011110110111001101101011011000010000001101011011010100110100101100100011000110110001001100001 E
b111001000100000011100010010000001110000011011110110111001101101011011000010000001101011011010100110100101100100011000110110001001100001 G
b10001 K
#22000
0)
b1110011 ,
b10001 2
0;
b1110011 =
#22500
1)
b10111 1
1;
b11100110111001000100000011100010010000001110000011011110110111001101101011011000010000001101011011010100110100101100100011000110110001001100001 E
b11100110111001000100000011100010010000001110000011011110110111001101101011011000010000001101011011010100110100101100100011000110110001001100001 G
b10010 K
#23000
0)
b1110100 ,
b10010 2
0;
b1110100 =
#23500
1)
b11000 1
1;
b1110100011100110111001000100000011100010010000001110000011011110110111001101101011011000010000001101011011010100110100101100100011000110110001001100001 E
b1110100011100110111001000100000011100010010000001110000011011110110111001101101011011000010000001101011011010100110100101100100011000110110001001100001 G
b10011 K
#24000
0)
b1110101 ,
b10011 2
0;
b1110101 =
#24500
1)
b11001 1
1;
b111010101110100011100110111001000100000011100010010000001110000011011110110111001101101011011000010000001101011011010100110100101100100011000110110001001100001 E
b111010101110100011100110111001000100000011100010010000001110000011011110110111001101101011011000010000001101011011010100110100101100100011000110110001001100001 G
b10100 K
#25000
0)
b1110110 ,
b10100 2
0;
b1110110 =
#25500
1)
b11010 1
1;
b11101100111010101110100011100110111001000100000011100010010000001110000011011110110111001101101011011000010000001101011011010100110100101100100011000110110001001100001 E
b11101100111010101110100011100110111001000100000011100010010000001110000011011110110111001101101011011000010000001101011011010100110100101100100011000110110001001100001 G
b10101 K
#26000
b10000 "
0)
b110001 ,
0-
1.
b0 2
b0 3
04
0;
b110001 =
0>
1?
1C
1D
#26500
1)
b11011 1
1;
b110001 F
b110001 H
b1 L
#27000
0)
b110010 ,
b1 2
0;
b110010 =
#27500
1)
b11100 1
1;
b11001000110001 F
b11001000110001 H
b10 L
#28000
0)
b110011 ,
b10 2
0;
b110011 =
#28500
1)
b11101 1
1;
b1100110011001000110001 F
b1100110011001000110001 H
b11 L
#29000
0)
b110100 ,
b11 2
0;
b110100 =
#29500
1)
b11110 1
1;
b110100001100110011001000110001 F
b110100001100110011001000110001 H
b100 L
#30000
0)
0.
16
0;
0?
0C
0D
#30500
1)
b11111 1
1;
b0 K
b0 L
#31000
0)
0;
#31500
1)
b100000 1
1;
b0 K
b0 L
#32000
0)
0;
#32500
1)
b100001 1
1;
b0 K
b0 L
#33000
0)
0;
#33500
1)
b100010 1
1;
b0 K
b0 L
#34000
0)
0;
#34500
1)
b100011 1
1;
b0 K
b0 L
#35000
0)
0;
#35500
1)
b100100 1
1;
b0 K
b0 L
#36000
0)
0;
#36500
1)
b100101 1
1;
b0 K
b0 L
#37000
0)
0;
#37500
1)
b100110 1
1;
b0 K
b0 L
#38000
0)
0;
#38500
1)
b100111 1
1;
b0 K
b0 L
#39000
0)
0;
#39500
1)
b101000 1
1;
b0 K
b0 L
#40000
0)
0;
#40500
1)
b101001 1
1;
b0 K
b0 L
#41000
0)
0;
#41500
1)
b101010 1
1;
b0 K
b0 L
#42000
0)
0;
#42500
1)
b101011 1
1;
b0 K
b0 L
#43000
0)
0;
#43500
1)
b101100 1
1;
b0 K
b0 L
#44000
0)
0;
#44500
1)
b101101 1
1;
b0 K
b0 L
#45000
0)
0;
#45500
1)
b101110 1
1;
b0 K
b0 L
#46000
0)
0;
#46500
1)
b101111 1
1;
b0 K
b0 L
#47000
0)
0;
#47500
1)
b110000 1
1;
b0 K
b0 L
#48000
0)
0;
#48500
1)
b110001 1
1;
b0 K
b0 L
#49000
0)
0;
#49500
1)
b110010 1
1;
b0 K
b0 L
#50000
0)
0;
#50500
1)
b110011 1
1;
b0 K
b0 L
#51000
0)
0;
#51500
1)
b110100 1
1;
b0 K
b0 L
#52000
0)
0;
#52500
1)
b110101 1
1;
b0 K
b0 L
#53000
0)
0;
#53500
1)
b110110 1
1;
b0 K
b0 L
#54000
0)
0;
#54500
1)
b110111 1
1;
b0 K
b0 L
#55000
0)
0;
#55500
1)
b111000 1
1;
b0 K
b0 L
#56000
0)
0;
#56500
1)
b111001 1
1;
b0 K
b0 L
#57000
0)
0;
#57500
1)
b111010 1
1;
b0 K
b0 L
#58000
0)
0;
#58500
1)
b111011 1
1;
b0 K
b0 L
#59000
0)
0;
#59500
1)
b111100 1
1;
b0 K
b0 L
#60000
0)
0;
#60500
1)
b111101 1
1;
b0 K
b0 L
#61000
0)
0;
#61500
1)
b111110 1
1;
b0 K
b0 L
#62000
0)
0;
#62500
1)
b111111 1
1;
b0 K
b0 L
#63000
0)
0;
#63500
1)
b1000000 1
1;
b0 K
b0 L
#64000
0)
0;
#64500
1)
b1000001 1
1;
b0 K
b0 L
#65000
0)
0;
#65500
1)
b1000010 1
1;
b0 K
b0 L
#66000
0)
0;
#66500
1)
b1000011 1
1;
b0 K
b0 L
#67000
0)
0;
#67500
1)
b1000100 1
1;
b0 K
b0 L
#68000
0)
0;
#68500
1)
b1000101 1
1;
b0 K
b0 L
#69000
0)
0;
#69500
1)
b1000110 1
1;
b0 K
b0 L
#70000
0)
0;
#70500
1)
b1000111 1
1;
b0 K
b0 L
#71000
0)
0;
#71500
1)
b1001000 1
1;
b0 K
b0 L
#72000
0)
0;
#72500
1)
b1001001 1
1;
b0 K
b0 L
#73000
0)
0;
#73500
1)
b1001010 1
1;
b0 K
b0 L
#74000
0)
0;
#74500
1)
b1001011 1
1;
b0 K
b0 L
#75000
0)
0;
#75500
1)
b1001100 1
1;
b0 K
b0 L
#76000
0)
0;
#76500
1)
b1001101 1
1;
b0 K
b0 L
#77000
0)
0;
#77500
1)
b1001110 1
1;
b0 K
b0 L
#78000
0)
0;
#78500
1)
b1001111 1
1;
b0 K
b0 L
#79000
0)
0;
#79500
1)
b1010000 1
1;
b0 K
b0 L
#80000
0)
0;
#80500
1)
b1010001 1
1;
b0 K
b0 L
#81000
0)
0;
#81500
1)
b1010010 1
1;
b0 K
b0 L
#82000
0)
0;
#82500
1)
b1010011 1
1;
b0 K
b0 L
#83000
0)
0;
#83500
1)
b1010100 1
1;
b0 K
b0 L
#84000
0)
0;
#84500
1)
b1010101 1
1;
b0 K
b0 L
#85000
0)
0;
#85500
1)
b1010110 1
1;
b0 K
b0 L
#86000
0)
0;
#86500
1)
b1010111 1
1;
b0 K
b0 L
#87000
0)
0;
#87500
1)
b1011000 1
1;
b0 K
b0 L
#88000
0)
0;
#88500
1)
b1011001 1
1;
b0 K
b0 L
#89000
0)
0;
#89500
1)
b1011010 1
1;
b0 K
b0 L
#90000
0)
0;
#90500
1)
b1011011 1
1;
b0 K
b0 L
#91000
0)
0;
#91500
1)
b1011100 1
1;
b0 K
b0 L
#92000
0)
0;
#92500
1)
b1011101 1
1;
b0 K
b0 L
#93000
0)
0;
#93500
1)
b1011110 1
1;
b0 K
b0 L
#94000
0)
0;
#94500
1)
b1011111 1
1;
b0 K
b0 L
#95000
0)
0;
#95500
1)
b1100000 1
1;
b0 K
b0 L
#96000
0)
0;
#96500
1)
b1100001 1
1;
b0 K
b0 L
#97000
0)
0;
#97500
1)
b1100010 1
1;
b0 K
b0 L
#98000
0)
0;
#98500
1)
b1100011 1
1;
b0 K
b0 L
#99000
0)
0;
#99500
1)
b1100100 1
1;
b0 K
b0 L
#100000
0)
0;
#100500
1)
b1100101 1
1;
b0 K
b0 L
#101000
0)
0;
#101500
1)
b1100110 1
1;
b0 K
b0 L
#102000
0)
0;
#102500
1)
b1100111 1
1;
b0 K
b0 L
#103000
0)
0;
#103500
1)
b1101000 1
1;
b0 K
b0 L
#104000
0)
0;
#104500
1)
b1101001 1
1;
b0 K
b0 L
#105000
0)
0;
#105500
1)
b1101010 1
1;
b0 K
b0 L
#106000
0)
0;
#106500
1)
b1101011 1
1;
b0 K
b0 L
#107000
0)
0;
#107500
1)
b1101100 1
1;
b0 K
b0 L
#108000
0)
0;
#108500
1)
b1101101 1
1;
b0 K
b0 L
#109000
0)
0;
#109500
1)
b1101110 1
1;
b0 K
b0 L
#110000
0)
0;
#110500
1)
b1101111 1
1;
b0 K
b0 L
#111000
0)
0;
#111500
1)
b1110000 1
1;
b0 K
b0 L
#112000
0)
0;
#112500
1)
b1110001 1
1;
b0 K
b0 L
#113000
0)
0;
#113500
1)
b1110010 1
1;
b0 K
b0 L
#114000
0)
0;
#114500
1)
b1110011 1
1;
b0 K
b0 L
#115000
0)
0;
#115500
1)
b1110100 1
1;
b0 K
b0 L
#116000
0)
0;
#116500
1)
b1110101 1
1;
b0 K
b0 L
#117000
0)
0;
#117500
1)
b1110110 1
1;
b0 K
b0 L
#118000
0)
0;
#118500
1)
b1110111 1
1;
b0 K
b0 L
#119000
0)
0;
#119500
1)
b1111000 1
1;
b0 K
b0 L
#120000
0)
0;
#120500
1)
b1111001 1
1;
b0 K
b0 L
#121000
0)
0;
#121500
1)
b1111010 1
1;
b0 K
b0 L
#122000
0)
0;
#122500
1)
b1111011 1
1;
b0 K
b0 L
#123000
0)
0;
#123500
1)
b1111100 1
1;
b0 K
b0 L
#124000
0)
0;
#124500
1)
b1111101 1
1;
b0 K
b0 L
#125000
0)
0;
#125500
1)
b1111110 1
1;
b0 K
b0 L
#126000
0)
0;
#126500
1)
b1111111 1
1;
b0 K
b0 L
#127000
0)
0;
#127500
1)
b10000000 1
1;
b0 K
b0 L
#128000
0)
0;
#128500
1)
b10000001 1
1;
b0 K
b0 L
#129000
0)
0;
#129500
1)
b10000010 1
1;
b0 K
b0 L
#130000
0)
0;
#130500
1)
b10000011 1
1;
b0 K
b0 L
#131000
0)
0;
#131500
1)
b10000100 1
1;
b0 K
b0 L
#132000
0)
0;
#132500
1)
b10000101 1
1;
b0 K
b0 L
#133000
0)
0;
#133500
1)
b10000110 1
1;
b0 K
b0 L
#134000
0)
0;
#134500
1)
b10000111 1
1;
b0 K
b0 L
#135000
0)
0;
#135500
1)
b10001000 1
1;
b0 K
b0 L
#136000
0)
0;
#136500
1)
b10001001 1
1;
b0 K
b0 L
#137000
0)
0;
#137500
1)
b10001010 1
1;
b0 K
b0 L
#138000
0)
0;
#138500
1)
b10001011 1
1;
b0 K
b0 L
#139000
0)
0;
#139500
1)
b10001100 1
1;
b0 K
b0 L
#140000
0)
0;
#140500
1)
b10001101 1
1;
b0 K
b0 L
#141000
0)
0;
#141500
1)
b10001110 1
1;
b0 K
b0 L
#142000
0)
0;
#142500
1)
b10001111 1
1;
b0 K
b0 L
#143000
0)
0;
#143500
1)
b10010000 1
1;
b0 K
b0 L
#144000
0)
0;
#144500
1)
b10010001 1
1;
b0 K
b0 L
#145000
0)
0;
#145500
1)
b10010010 1
1;
b0 K
b0 L
#146000
0)
0;
#146500
1)
b10010011 1
1;
b0 K
b0 L
#147000
0)
0;
#147500
1)
b10010100 1
1;
b0 K
b0 L
#148000
0)
0;
#148500
1)
b10010101 1
1;
b0 K
b0 L
#149000
0)
0;
#149500
1)
b10010110 1
1;
b0 K
b0 L
#150000
0)
0;
#150500
1)
b10010111 1
1;
b0 K
b0 L
#151000
0)
0;
#151500
1)
b10011000 1
1;
b0 K
b0 L
#152000
0)
0;
#152500
1)
b10011001 1
1;
b0 K
b0 L
#153000
0)
0;
#153500
1)
b10011010 1
1;
b0 K
b0 L
#154000
0)
0;
#154500
1)
b10011011 1
1;
b0 K
b0 L
#155000
0)
0;
#155500
1)
b10011100 1
1;
b0 K
b0 L
#156000
0)
0;
#156500
1)
b10011101 1
1;
b0 K
b0 L
#157000
0)
0;
#157500
1)
b10011110 1
1;
b0 K
b0 L
#158000
0)
0;
#158500
1)
b10011111 1
1;
b0 K
b0 L
#159000
0)
0;
#159500
1)
b10100000 1
1;
b0 K
b0 L
#160000
0)
0;
#160500
1)
b10100001 1
1;
b0 K
b0 L
#161000
0)
0;
#161500
1)
b10100010 1
1;
b0 K
b0 L
#162000
0)
0;
#162500
1)
b10100011 1
1;
b0 K
b0 L
#163000
0)
0;
#163500
1)
b10100100 1
1;
b0 K
b0 L
#164000
0)
0;
#164500
1)
b10100101 1
1;
b0 K
b0 L
#165000
0)
0;
#165500
1)
b10100110 1
1;
b0 K
b0 L
#166000
0)
0;
#166500
1)
b10100111 1
1;
b0 K
b0 L
#167000
0)
0;
#167500
1)
b10101000 1
1;
b0 K
b0 L
#168000
0)
0;
#168500
1)
b10101001 1
1;
b0 K
b0 L
#169000
0)
0;
#169500
1)
b10101010 1
1;
b0 K
b0 L
#170000
0)
0;
#170500
1)
b10101011 1
1;
b0 K
b0 L
#171000
0)
0;
#171500
1)
b10101100 1
1;
b0 K
b0 L
#172000
0)
0;
#172500
1)
b10101101 1
1;
b0 K
b0 L
#173000
0)
0;
#173500
1)
b10101110 1
1;
b0 K
b0 L
#174000
0)
0;
#174500
1)
b10101111 1
1;
b0 K
b0 L
#175000
0)
0;
#175500
1)
b10110000 1
1;
b0 K
b0 L
#176000
0)
0;
#176500
1)
b10110001 1
1;
b0 K
b0 L
#177000
0)
0;
#177500
1)
b10110010 1
1;
b0 K
b0 L
#178000
0)
0;
#178500
1)
b10110011 1
1;
b0 K
b0 L
#179000
0)
0;
#179500
1)
b10110100 1
1;
b0 K
b0 L
#180000
0)
0;
#180500
1)
b10110101 1
1;
b0 K
b0 L
#181000
0)
0;
#181500
1)
b10110110 1
1;
b0 K
b0 L
#182000
0)
0;
#182500
1)
b10110111 1
1;
b0 K
b0 L
#183000
0)
0;
#183500
1)
b10111000 1
1;
b0 K
b0 L
#184000
0)
0;
#184500
1)
b10111001 1
1;
b0 K
b0 L
#185000
0)
0;
#185500
1)
b10111010 1
1;
b0 K
b0 L
#186000
0)
0;
#186500
1)
b10111011 1
1;
b0 K
b0 L
#187000
0)
0;
#187500
1)
b10111100 1
1;
b0 K
b0 L
#188000
0)
0;
#188500
1)
b10111101 1
1;
b0 K
b0 L
#189000
0)
0;
#189500
1)
b10111110 1
1;
b0 K
b0 L
#190000
0)
0;
#190500
1)
b10111111 1
1;
b0 K
b0 L
#191000
0)
0;
#191500
1)
b11000000 1
1;
b0 K
b0 L
#192000
0)
0;
#192500
1)
b11000001 1
1;
b0 K
b0 L
#193000
0)
0;
#193500
1)
b11000010 1
1;
b0 K
b0 L
#194000
0)
0;
#194500
1)
b11000011 1
1;
b0 K
b0 L
#195000
0)
0;
#195500
1)
b11000100 1
1;
b0 K
b0 L
#196000
0)
0;
#196500
1)
b11000101 1
1;
b0 K
b0 L
#197000
0)
0;
#197500
1)
b11000110 1
1;
b0 K
b0 L
#198000
0)
0;
#198500
1)
b11000111 1
1;
b0 K
b0 L
#199000
0)
0;
#199500
1)
b11001000 1
1;
b0 K
b0 L
#200000
0)
0;
#200500
1)
b11001001 1
1;
b0 K
b0 L
#201000
0)
0;
#201500
1)
b11001010 1
1;
b0 K
b0 L
#202000
0)
0;
#202500
1)
b11001011 1
1;
b0 K
b0 L
#203000
0)
0;
#203500
1)
b11001100 1
1;
b0 K
b0 L
#204000
0)
0;
#204500
1)
b11001101 1
1;
b0 K
b0 L
#205000
0)
0;
#205500
1)
b11001110 1
1;
b0 K
b0 L
#206000
0)
0;
#206500
1)
b11001111 1
1;
b0 K
b0 L
#207000
0)
0;
#207500
1)
b11010000 1
1;
b0 K
b0 L
#208000
0)
0;
#208500
1)
b11010001 1
1;
b0 K
b0 L
#209000
0)
0;
#209500
1)
b11010010 1
1;
b0 K
b0 L
#210000
0)
0;
