src/SME_spec_param.v
`define BYTE 8
`define NUM_SLAVE 4
`define MAX_STRING 32
  `define MAX_STR_ADD 5
`define MAX_PATTERN 8
  `define MAX_PAT_ADD 3

src/PE_slave.v
`include "SME_spec_param.v"

module pe_slave(clk, reset, str_input, pat_input, input_valid, start_idx, process_2idx, ff_result, output_valid, match, match_idx);
input clk;
input reset;
input [`MAX_STRING * `BYTE - 1 : 0] str_input;
input [`MAX_PATTERN * `BYTE - 1 : 0] pat_input;
input input_valid;
input [`MAX_STR_ADD - 1 : 0] start_idx;
input [`MAX_STR_ADD - 1 : 0] process_2idx;
input [`MAX_PAT_ADD * `MAX_PATTERN - 1 : 0] ff_result;

output reg output_valid;
output reg match;
output reg [`MAX_STR_ADD - 1 : 0] match_idx;
//---------------------input/output---------------------//

localparam NUM_STATE = 4;
reg [NUM_STATE - 1 : 0] current_st;
reg [NUM_STATE - 1 : 0] next_st;
  localparam IDLE_ST = 'b0001;
  localparam PRE_ST = 'b0010;
  localparam COM_ST = 'b0100;
  localparam DONE_ST = 'b1000;
//---------------------FSM PARM---------------------//

reg signed [`MAX_PAT_ADD - 1 : 0] kmp_map [0 : `MAX_PATTERN - 1];


always@(posedge clk)
begin
  if(reset) current_st <= IDLE_ST;
  else current_st <= next_st;
end

always@(*)
begin
  case(current_st)
  IDLE_ST: if(input_valid) next_st = PRE_ST;
  endcase
end



endmodule

src/DP_FailFunc.v
`include "SME_spec_param.v"

module DP_FailFunc(clk, reset, i_valid, pattern, last_pat_idx, o_fail_func, o_valid);
  input clk;
  input reset;
  input i_valid;
  input [`MAX_PATTERN * `BYTE - 1 : 0] pattern;
  input [`MAX_PAT_ADD - 1: 0] last_pat_idx;
  output reg [`MAX_PAT_ADD * `MAX_PATTERN - 1 : 0] o_fail_func;
  output reg o_valid;
  //---------------------input/output---------------------//

  reg [`MAX_PAT_ADD - 1 : 0] process_idx;
  reg [`MAX_PAT_ADD - 1 : 0] last_ff_map;
  reg done_flag;
  //---------------------control signal---------------------//

  reg [2:0] current_st;
  reg [2:0] next_st;
    localparam IDLE_ST = 4'b001;
    localparam CALCU_ST = 4'b010;
    localparam DONE_ST = 4'b100;
  //---------------------FSM declare---------------------//

  integer i;
  //---------------------end declare---------------------//

  //FSM state current change.
  always@(posedge clk)
  begin
    if(reset) current_st <= IDLE_ST;
    else current_st <= next_st;
  end

  //FSM state next state change condition.
  always@(*)
  begin
    case(current_st)
    IDLE_ST : if(i_valid) next_st <= CALCU_ST; else next_st <= IDLE_ST;
    CALCU_ST : if(done_flag) next_st <= DONE_ST; else next_st <= CALCU_ST;
    DONE_ST : if(!i_valid) next_st <= IDLE_ST; else next_st <= DONE_ST;
    default : ; // Do Nothing
    endcase
  end

  //output syn. reset
  always@(posedge clk)
  begin
    if(reset)
    begin
      o_valid <= 0;
      
      for(i = 0; i < (`MAX_PAT_ADD * `MAX_PATTERN); i = i + 1)
      begin
        o_fail_func[i] <= 0;
      end
    end
  end

  //main(state: CALCU_ST): (DP)failure function implement.
  //!!!Respect!!! Richard Bellman
  always@(posedge clk)
  begin
    if(reset)
    begin
      process_idx <= 0;
      done_flag <= 0;
      last_ff_map <= 0;
    end

    else if(current_st == CALCU_ST)
    begin
      if(!done_flag)
      begin
        if(process_idx == 0)begin o_fail_func[2:0] <= 0; process_idx <= process_idx + 1; last_ff_map <= 0; end
        else if(process_idx == last_pat_idx)begin process_idx <= 0; last_ff_map <= 0; done_flag <= 1; end

        else
        begin
          if(pattern[last_ff_map * `BYTE +: `BYTE] == pattern[process_idx * `BYTE +: `BYTE])
          begin
            o_fail_func[process_idx * `MAX_PAT_ADD +: `MAX_PAT_ADD] <= last_ff_map + 1;
            last_ff_map <= last_ff_map + 1;
            process_idx <= process_idx + 1;
          end
          else
          begin
            o_fail_func[process_idx * `MAX_PAT_ADD +: `MAX_PAT_ADD] <= 0;
            last_ff_map <= 0;
            process_idx <= process_idx + 1;
          end
        end
      end
    end

    else
    begin
      process_idx <= 0;
      done_flag <= 0;
      last_ff_map <= 0;
    end
  end
endmodule

src/shared_memory.v
`include "SME_spec_param.v"

module shared_memory(clk, reset, w_data, write, w_sel, str_reg, pat_reg, str_last_idx, pat_last_idx, ff_result, valid);
  input clk;
  input reset;
  input [`BYTE - 1:0] w_data;
  input write;
  input w_sel;

  output reg [`MAX_STRING * `BYTE - 1 : 0] str_reg;
  output reg [`MAX_PATTERN * `BYTE - 1 : 0] pat_reg;
  output reg [`MAX_STR_ADD - 1: 0] str_last_idx;
  output reg [`MAX_PAT_ADD - 1: 0] pat_last_idx;
  output [`MAX_PAT_ADD * `MAX_PATTERN - 1 : 0] ff_result;
  output reg valid;
//---------------------input/output---------------------//
  integer i, j;
  parameter sel_str_reg = 0;
  parameter sel_pat_reg = 1;

  reg [`MAX_STR_ADD - 1 : 0] s_index;
  reg [`MAX_PAT_ADD - 1 : 0] p_index;
  reg [2:0] active;
    localparam NON_READ = 0;
    localparam READING = 1;
    localparam FF_CAL = 2;
    localparam DONE = 3;

  reg read_done;

  wire ff_valid;
  DP_FailFunc dp1(.clk(clk), 
                  .reset(reset), 
                  .i_valid(read_done), 
                  .pattern(pat_reg), 
                  .last_pat_idx(pat_last_idx), 
                  .o_fail_func(ff_result), 
                  .o_valid(ff_valid));

  always@(posedge clk)
  begin
      if(reset)
      begin
        s_index <= 0;
        p_index <= 0;
        str_last_idx <= 0;
        pat_last_idx <= 0;
        active <= NON_READ;
        valid <= 0;
        read_done <= 0;

        for(i = 0; i < (`MAX_STRING * `BYTE); i = i + 1)
        begin
          str_reg[i] <= 0;
        end

        for(j = 0; j < (`MAX_PATTERN * `BYTE); j = j + 1)
        begin
          pat_reg[j] <= 0;
        end
      end
      
      else if(write)
      begin
        active <= READING;
        read_done <= 0;
        valid <= 0;
        case(w_sel)
          sel_str_reg : begin str_reg[s_index * `BYTE +: `BYTE] <= w_data; s_index <= s_index + 1; str_last_idx <= s_index; end
          sel_pat_reg : begin pat_reg[p_index * `BYTE +: `BYTE] <= w_data; p_index <= p_index + 1; pat_last_idx <= p_index; end
          default : ;
        endcase
      end

      else
      begin
        if(active == READING) begin active <= FF_CAL; read_done <= 1; end
        else if(active == FF_CAL)begin if(ff_valid) begin active <= DONE; valid <= 1; end end
        else begin active <= NON_READ; end

        s_index <= 0;
        p_index <= 0;
      end
end

endmodule

src/SME.v
`include "SME_spec_param.v"

module SME(
  input clk,
  input reset,
  input [`BYTE - 1 : 0] chardata,
  input isstring,
  input ispattern,
  output reg valid,
  output reg match,
  output reg [`MAX_STR_ADD - 1 : 0] match_index
  );

  wire write;
  assign write = (ispattern || isstring)? 1:0;
  wire w_sel;
  assign w_sel = (ispattern)? 1:0;

  wire [`MAX_STRING * `BYTE - 1 : 0]str;
  wire [`MAX_PATTERN * `BYTE - 1 : 0] pat;
  wire [`MAX_STR_ADD - 1: 0] str_last_index;
  wire [`MAX_PAT_ADD - 1: 0] pat_last_index;
  wire input_valid;
  wire [`MAX_PAT_ADD * `MAX_PATTERN - 1 : 0] ff_result;
  shared_memory s1(.clk(clk), 
                   .reset(reset), 
                   .w_data(chardata), 
                   .write(write), 
                   .w_sel(w_sel), 
                   .str_reg(str), 
                   .pat_reg(pat), 
                   .str_last_idx(str_last_index), 
                   .pat_last_idx(pat_last_index), 
                   .ff_result(ff_result), 
                   .valid(input_valid));

  wire o_valid;
  wire s_match;
  wire [`MAX_STR_ADD - 1 : 0] s_match_idx;
  pe_slave ps1(.clk(clk), 
               .reset(reset), 
               .str_input(str), 
               .pat_input(pat), 
               .input_valid(input_valid), 
               .start_idx(5'b0), 
               .process_2idx(str_last_index), 
               .ff_result(ff_result),
               .output_valid(o_valid), 
               .match(s_match), 
               .match_idx(s_match_idx));



endmodule

test_bench/sme_tb.sv
`timescale 1ns/10ps
`define CYCLE      20.0  
`define SDFFILE    "./SME_syn.sdf"
`define End_CYCLE  1000000
`define PAT        "test_pattern1.txt"
module testfixture();

integer linedata;
integer char_count;
//reg [128:0] data;
string data;
string strnum;
string patnum;
string strdata;
string goldmatch_s;
string goldmatch_index_s;

reg clk = 0;
wire valid;
reg reset =0;
reg [7:0] chardata;
reg isstring=0;
reg ispattern=0;
wire match;
wire [4:0] match_index;
SME u_SME (.clk(clk),
           .reset(reset),
           .chardata(chardata),
           .isstring(isstring),
           .ispattern(ispattern),
           .valid(valid),
           .match(match),
           .match_index(match_index));

`ifdef SDF
    initial $sdf_annotate(`SDFFILE, u_SME);
`endif

always begin #(`CYCLE/2) clk = ~clk; end
/*
initial begin
    $fsdbDumpfile("SME.fsdb");
    $fsdbDumpvars;
    $fsdbDumpMDA;
end
*/
//initial begin
//    $dumpfile("SME.vcd");
//    $dumpvars;
//end

initial begin
    $display("----------------------");
    $display("-- Simulation Start --");
    $display("----------------------");
    @(posedge clk); #1; reset = 1'b1; 
    #(`CYCLE*2);  
    @(posedge clk); #1;   reset = 1'b0;
end

reg [22:0] cycle=0;

always @(posedge clk) begin
    cycle=cycle+1;
    if (cycle > `End_CYCLE) begin
        $display("--------------------------------------------------");
        $display("-- Failed waiting valid signal, Simulation STOP --");
        $display("--------------------------------------------------");
        $fclose(linedata);
        $finish;
    end
end

initial begin
    linedata = $fopen(`PAT,"r");
    if (linedata == 0) begin
        $display ("pattern handle null");
        $finish;
    end
end

integer strindex;
reg [7:0] goldmatch_index;
reg  goldmatch;
reg  valid_reg;
reg wait_valid;
reg  getmatch;
reg [7:0] getmatch_index;
always @(posedge clk) begin
    valid_reg = valid;
end

integer score=0;
integer allpass=1;
always @(negedge clk) begin
    if (reset) begin
        wait_valid=0;
    end
    else begin
        if (wait_valid==1 && valid ==1) begin
            wait_valid=0;
            getmatch=match;
            getmatch_index=match_index;
            //$display ("       string/pattern = %s/%s",strnum,patnum);
            if(goldmatch==1)begin
                if(getmatch == goldmatch) begin
                    score++;
                    if(getmatch_index==goldmatch_index) begin
                        score=score+2;
                        //colordisplay(cycle,goldmatch,goldmatch_index,getmatch,getmatch_index,3);
                        $display ("       cycle %2h, expect(%h,%h) , get(%h,%h) >> Pass",cycle,goldmatch,goldmatch_index,getmatch,getmatch_index);
                    end
                    else begin 
                        allpass=0;
                        //colordisplay(cycle,goldmatch,goldmatch_index,getmatch,getmatch_index,2);
                        $display ("       cycle %2h, expect(%h,%h) , get(%h,%h) >> Wrong index",cycle,goldmatch,goldmatch_index,getmatch,getmatch_index);
                    end
                end
                else begin
                    allpass=0;
                    //colordisplay(cycle,goldmatch,goldmatch_index,getmatch,getmatch_index,0);
                    $display ("       cycle %2h, expect(%h,%h) , get(%h,%h) >> Fail",cycle,goldmatch,goldmatch_index,getmatch,getmatch_index);
                end
            end
            else begin
                if(getmatch == goldmatch) begin
                    score++;
                    //colordisplay(cycle,goldmatch,goldmatch_index,getmatch,getmatch_index,3);
                    $display ("       cycle %2h, expect(%h,--) , get(%h,--) >> Pass",cycle, goldmatch,getmatch);
                end
                else begin
                    allpass=0;
                    //colordisplay(cycle,goldmatch,goldmatch_index,getmatch,getmatch_index,1);
                    $display ("       cycle %2h, expect(%h,--) , get(%h,--) >> Fail",cycle, goldmatch,getmatch);
                end
            end
        //$display ("       score = %d",score);
        end
    end
end

always @(negedge clk ) begin
    if (reset) begin
        isstring=0;
        ispattern=0;
        valid_reg=0;
    end 
    else begin
        if (strindex==strdata.len()-1) begin
            isstring=0;
            if(ispattern==1) wait_valid=1;
            ispattern=0;
        end
        if (wait_valid == 1'b0) begin
            if (strindex<strdata.len()-1) begin
                strindex=strindex+1;
                chardata = strdata.getc(strindex);
                //$display("%h %s,%h",cycle,chardata,chardata);
            end 
            else begin
                if (!$feof(linedata))begin
                    char_count = $fgets (data, linedata);
                    if (char_count !== 0) begin
                        if(data.substr(0,3) == "str:") begin
                            isstring=1; 
                            strindex=0;
                            strnum = data.substr(4,4);
                            strdata = data.substr(6,data.len()-2);
                            $display("  __________________________________________________________");
                            $display("  == String %s  \"%s\"", strnum, strdata);
                            chardata = strdata.getc(strindex);
                            //$display("%h %s,%h",cycle,chardata,chardata);
                        end 
                        else begin
                            if(data.substr(0,3) == "pat:") begin
                                ispattern=1; 
                                strindex=0;
                                patnum = data.substr(4,4);
                                goldmatch_s = data.substr(6,6);
                                goldmatch = goldmatch_s.atoi();
                                goldmatch_index_s = data.substr(8,9);
                                goldmatch_index = goldmatch_index_s.atoi();
                                strdata = data.substr(11,data.len()-2);
                                //$display("==== Pattern__%s__%b__%2d__%s", patnum, goldmatch,goldmatch_index,strdata);
                                $display("  -- Pattern %s  \"%s\"", patnum, strdata);
                                chardata = strdata.getc(strindex);
                                //$display("%h %s,%h",cycle,chardata,chardata);
                            end
                        end
                    end
                end
                else begin
                    $display("----------------------------------");
                    if(allpass == 1 && score >1)
                    $display("-- Simulation finish, ALL PASS  --");
                    else
                    $display("-- Simulation finish            --");
                    $display("-- cycle =%3d , Score =%2d       --",cycle, score);
                    $display("----------------------------------");
                    $fclose(linedata);
                    $finish;
                end
            end
        end // if wait_valid == 0
    end
end
endmodule

task colordisplay;
    input [12:0] cycle;
    input goldmatch;
    input [7:0] goldmatchindex;
    input getmatch;
    input [7:0] getmatchindex;
    input [1:0]pass; 
    begin
        $write ("       cycle %2h, expect(%h,%h) , get(",cycle,goldmatch,goldmatchindex);
        case(pass)
            2'd0: begin   // expect match , failed
                $write("%c[1;31m",27);
                $write ("%h,%h",getmatch,getmatchindex);
                $write("%c[0m",27);
                $write (") >> Fail\n");

                  end
            2'd1: begin   // expect unmatch, failed
                $write("%c[1;31m",27);
                $write ("%h",getmatch);
                $write ("%c[0m",27);
                $write (",%h) >> Fail\n",getmatchindex);

                  end
            2'd2: begin  // expect match, wrong index
                $write ("%h,",getmatch);
                $write("%c[1;31m",27);
                $write ("%h",getmatchindex);
                $write("%c[0m",27);
                $write (") >> Wrong index\n");

                  end
            2'd3: begin // both match or unmatch, passed
                $write ("%h,%h",getmatch,getmatchindex);
                $write (") >> Pass\n");

                  end
        endcase
    end
endtask

vivado_project/SME_parallel.sim/sim_1/behav/xsim/SME.vcd
$date
   Sat Dec  5 21:16:26 2020
$end
$version
  2019.1
$end
$timescale
  1ps
$end
$scope module testfixture $end
$var integer 32 ! linedata $end
$var integer 32 " char_count $end
$var reg 32 # data $end
$var reg 32 $ strnum $end
$var reg 32 % patnum $end
$var reg 32 & strdata $end
$var reg 32 ' goldmatch_s $end
$var reg 32 ( goldmatch_index_s $end
$var reg 1 ) clk $end
$var wire 1 * valid $end
$var reg 1 + reset $end
$var reg 8 , chardata [7:0] $end
$var reg 1 - isstring $end
$var reg 1 . ispattern $end
$var wire 1 / match $end
$var wire 5 0 match_index [4:0] $end
$var reg 23 1 cycle [22:0] $end
$var integer 32 2 strindex $end
$var reg 8 3 goldmatch_index [7:0] $end
$var reg 1 4 goldmatch $end
$var reg 1 5 valid_reg $end
$var reg 1 6 wait_valid $end
$var reg 1 7 getmatch $end
$var reg 8 8 getmatch_index [7:0] $end
$var integer 32 9 score $end
$var integer 32 : allpass $end
$scope module u_SME $end
$var wire 1 ; clk $end
$var wire 1 < reset $end
$var wire 8 = chardata [7:0] $end
$var wire 1 > isstring $end
$var wire 1 ? ispattern $end
$var reg 1 @ valid $end
$var reg 1 A match $end
$var reg 5 B match_index [4:0] $end
$var wire 1 C write $end
$var wire 1 D w_sel $end
$var wire 256 E str [255:0] $end
$var wire 64 F pat [63:0] $end
$var wire 5 G str_last_index [4:0] $end
$var wire 3 H pat_last_index [2:0] $end
$var wire 1 I input_valid $end
$var wire 24 J ff_result [23:0] $end
$var wire 1 K o_valid $end
$var wire 1 L s_match $end
$var wire 5 M s_match_idx [4:0] $end
$scope module s1 $end
$var wire 1 ; clk $end
$var wire 1 < reset $end
$var wire 8 = w_data [7:0] $end
$var wire 1 C write $end
$var wire 1 D w_sel $end
$var reg 256 N str_reg [255:0] $end
$var reg 64 O pat_reg [63:0] $end
$var reg 5 P str_last_idx [4:0] $end
$var reg 3 Q pat_last_idx [2:0] $end
$var wire 24 J ff_result [23:0] $end
$var reg 1 R valid $end
$var integer 32 S i $end
$var integer 32 T j $end
$var reg 5 U s_index [4:0] $end
$var reg 3 V p_index [2:0] $end
$var reg 3 W active [2:0] $end
$var reg 1 X read_done $end
$var wire 1 Y ff_valid $end
$var parameter 32 Z sel_str_reg [31:0] $end
$var parameter 32 [ sel_pat_reg [31:0] $end
$var parameter 32 \ NON_READ [31:0] $end
$var parameter 32 ] READING [31:0] $end
$var parameter 32 ^ FF_CAL [31:0] $end
$var parameter 32 _ DONE [31:0] $end
$scope module dp1 $end
$var wire 1 ; clk $end
$var wire 1 < reset $end
$var wire 1 ` i_valid $end
$var wire 64 O pattern [63:0] $end
$var wire 3 Q last_pat_idx [2:0] $end
$var reg 24 a o_fail_func [23:0] $end
$var reg 1 b o_valid $end
$var reg 3 c process_idx [2:0] $end
$var reg 3 d last_ff_map [2:0] $end
$var reg 1 e done_flag $end
$var reg 3 f current_st [2:0] $end
$var reg 3 g next_st [2:0] $end
$var integer 32 h i $end
$var parameter 4 i IDLE_ST [3:0] $end
$var parameter 4 j CALCU_ST [3:0] $end
$var parameter 4 k DONE_ST [3:0] $end
$upscope $end
$upscope $end
$scope module ps1 $end
$var wire 1 ; clk $end
$var wire 1 < reset $end
$var wire 256 E str_input [255:0] $end
$var wire 64 F pat_input [63:0] $end
$var wire 1 I input_valid $end
$var wire 5 l start_idx [4:0] $end
$var wire 5 G process_2idx [4:0] $end
$var wire 24 J ff_result [23:0] $end
$var reg 1 m output_valid $end
$var reg 1 n match $end
$var reg 5 o match_idx [4:0] $end
$var reg 4 p current_st [3:0] $end
$var reg 4 q next_st [3:0] $end
$var parameter 32 r NUM_STATE [31:0] $end
$var parameter 32 s IDLE_ST [31:0] $end
$var parameter 32 t PRE_ST [31:0] $end
$var parameter 32 u COM_ST [31:0] $end
$var parameter 32 v DONE_ST [31:0] $end
$upscope $end
$upscope $end
$upscope $end
$enddefinitions $end
#0
$dumpvars
b11111111111111111011000111100000 !
bx "
b0 #
b0 $
b0 %
b0 &
b0 '
b0 (
0)
x*
0+
bx ,
0-
0.
x/
bx 0
b0 1
bx 2
bx 3
x4
x5
x6
x7
bx 8
b0 9
b1 :
0;
0<
bx =
0>
0?
x@
xA
bx B
0C
0D
bx E
bx F
bx G
bx H
xI
bx J
xK
xL
bx M
bx N
bx O
bx P
bx Q
xR
bx S
bx T
bx U
bx V
bx W
xX
xY
b0 Z
b1 [
b0 \
b1 ]
b10 ^
b11 _
x`
bx a
xb
bx c
bx d
xe
bx f
bx g
bx h
b1 i
b10 j
b100 k
b0 l
xm
xn
bx o
bx p
bx q
b100 r
b1 s
b10 t
b100 u
b1000 v
$end
#500
1)
b1 1
1;
b0 U
b0 V
b0 W
b0 c
b0 d
0e
bx f
bx p
#1000
0)
0;
#1500
1)
1+
b10 1
1;
1<
b0 E
b0 F
b0 G
b0 H
0I
b0 J
b0 N
b0 O
b0 P
b0 Q
0R
b100000000 S
b1000000 T
b0 U
b0 V
b0 W
0X
0Y
0`
b0 a
0b
b0 c
b0 d
0e
b1 f
b1 g
b11000 h
b1 p
#2000
0)
05
06
0;
#2500
1)
b11 1
x5
1;
b0 N
b0 O
b0 P
b0 Q
0R
b100000000 S
b1000000 T
b0 U
b0 V
b0 W
0X
b0 a
0b
b0 c
b0 d
0e
b1 f
b11000 h
b1 p
#3000
0)
05
0;
#3500
1)
b100 1
x5
1;
b0 N
b0 O
b0 P
b0 Q
0R
b100000000 S
b1000000 T
b0 U
b0 V
b0 W
0X
b0 a
0b
b0 c
b0 d
0e
b1 f
b11000 h
b1 p
#4000
0)
05
0;
#4500
1)
0+
b101 1
x5
1;
0<
b0 U
b0 V
b0 W
b0 c
b0 d
0e
b1 f
bx p
#5000
b11100 "
0)
b1100001 ,
1-
b0 2
0;
b1100001 =
1>
1C
#5500
1)
b110 1
1;
b1100001 E
b1100001 N
b0 P
0R
b1 U
b1 W
0X
b0 c
b0 d
0e
b1 f
bx p
#6000
0)
b1100010 ,
b1 2
0;
b1100010 =
#6500
1)
b111 1
1;
b110001001100001 E
b1 G
b110001001100001 N
b1 P
0R
b10 U
b1 W
0X
b0 c
b0 d
0e
b1 f
bx p
#7000
0)
b1100011 ,
b10 2
0;
b1100011 =
#7500
1)
b1000 1
1;
b11000110110001001100001 E
b10 G
b11000110110001001100001 N
b10 P
0R
b11 U
b1 W
0X
b0 c
b0 d
0e
b1 f
bx p
#8000
0)
b1100100 ,
b11 2
0;
b1100100 =
#8500
1)
b1001 1
1;
b1100100011000110110001001100001 E
b11 G
b1100100011000110110001001100001 N
b11 P
0R
b100 U
b1 W
0X
b0 c
b0 d
0e
b1 f
bx p
#9000
0)
b1101001 ,
b100 2
0;
b1101001 =
#9500
1)
b1010 1
1;
b110100101100100011000110110001001100001 E
b100 G
b110100101100100011000110110001001100001 N
b100 P
0R
b101 U
b1 W
0X
b0 c
b0 d
0e
b1 f
bx p
#10000
0)
b1101010 ,
b101 2
0;
b1101010 =
#10500
1)
b1011 1
1;
b11010100110100101100100011000110110001001100001 E
b101 G
b11010100110100101100100011000110110001001100001 N
b101 P
0R
b110 U
b1 W
0X
b0 c
b0 d
0e
b1 f
bx p
#11000
0)
b1101011 ,
b110 2
0;
b1101011 =
#11500
1)
b1100 1
1;
b1101011011010100110100101100100011000110110001001100001 E
b110 G
b1101011011010100110100101100100011000110110001001100001 N
b110 P
0R
b111 U
b1 W
0X
b0 c
b0 d
0e
b1 f
bx p
#12000
0)
b100000 ,
b111 2
0;
b100000 =
#12500
1)
b1101 1
1;
b10000001101011011010100110100101100100011000110110001001100001 E
b111 G
b10000001101011011010100110100101100100011000110110001001100001 N
b111 P
0R
b1000 U
b1 W
0X
b0 c
b0 d
0e
b1 f
bx p
#13000
0)
b1101100 ,
b1000 2
0;
b1101100 =
#13500
1)
b1110 1
1;
b11011000010000001101011011010100110100101100100011000110110001001100001 E
b1000 G
b11011000010000001101011011010100110100101100100011000110110001001100001 N
b1000 P
0R
b1001 U
b1 W
0X
b0 c
b0 d
0e
b1 f
bx p
#14000
0)
b1101101 ,
b1001 2
0;
b1101101 =
#14500
1)
b1111 1
1;
b1101101011011000010000001101011011010100110100101100100011000110110001001100001 E
b1001 G
b1101101011011000010000001101011011010100110100101100100011000110110001001100001 N
b1001 P
0R
b1010 U
b1 W
0X
b0 c
b0 d
0e
b1 f
bx p
#15000
0)
b1101110 ,
b1010 2
0;
b1101110 =
#15500
1)
b10000 1
1;
b110111001101101011011000010000001101011011010100110100101100100011000110110001001100001 E
b1010 G
b110111001101101011011000010000001101011011010100110100101100100011000110110001001100001 N
b1010 P
0R
b1011 U
b1 W
0X
b0 c
b0 d
0e
b1 f
bx p
#16000
0)
b1101111 ,
b1011 2
0;
b1101111 =
#16500
1)
b10001 1
1;
b11011110110111001101101011011000010000001101011011010100110100101100100011000110110001001100001 E
b1011 G
b11011110110111001101101011011000010000001101011011010100110100101100100011000110110001001100001 N
b1011 P
0R
b1100 U
b1 W
0X
b0 c
b0 d
0e
b1 f
bx p
#17000
0)
b1110000 ,
b1100 2
0;
b1110000 =
#17500
1)
b10010 1
1;
b1110000011011110110111001101101011011000010000001101011011010100110100101100100011000110110001001100001 E
b1100 G
b1110000011011110110111001101101011011000010000001101011011010100110100101100100011000110110001001100001 N
b1100 P
0R
b1101 U
b1 W
0X
b0 c
b0 d
0e
b1 f
bx p
#18000
0)
b100000 ,
b1101 2
0;
b100000 =
#18500
1)
b10011 1
1;
b10000001110000011011110110111001101101011011000010000001101011011010100110100101100100011000110110001001100001 E
b1101 G
b10000001110000011011110110111001101101011011000010000001101011011010100110100101100100011000110110001001100001 N
b1101 P
0R
b1110 U
b1 W
0X
b0 c
b0 d
0e
b1 f
bx p
#19000
0)
b1110001 ,
b1110 2
0;
b1110001 =
#19500
1)
b10100 1
1;
b11100010010000001110000011011110110111001101101011011000010000001101011011010100110100101100100011000110110001001100001 E
b1110 G
b11100010010000001110000011011110110111001101101011011000010000001101011011010100110100101100100011000110110001001100001 N
b1110 P
0R
b1111 U
b1 W
0X
b0 c
b0 d
0e
b1 f
bx p
#20000
0)
b100000 ,
b1111 2
0;
b100000 =
#20500
1)
b10101 1
1;
b100000011100010010000001110000011011110110111001101101011011000010000001101011011010100110100101100100011000110110001001100001 E
b1111 G
b100000011100010010000001110000011011110110111001101101011011000010000001101011011010100110100101100100011000110110001001100001 N
b1111 P
0R
b10000 U
b1 W
0X
b0 c
b0 d
0e
b1 f
bx p
#21000
0)
b1110010 ,
b10000 2
0;
b1110010 =
#21500
1)
b10110 1
1;
b111001000100000011100010010000001110000011011110110111001101101011011000010000001101011011010100110100101100100011000110110001001100001 E
b10000 G
b111001000100000011100010010000001110000011011110110111001101101011011000010000001101011011010100110100101100100011000110110001001100001 N
b10000 P
0R
b10001 U
b1 W
0X
b0 c
b0 d
0e
b1 f
bx p
#22000
0)
b1110011 ,
b10001 2
0;
b1110011 =
#22500
1)
b10111 1
1;
b11100110111001000100000011100010010000001110000011011110110111001101101011011000010000001101011011010100110100101100100011000110110001001100001 E
b10001 G
b11100110111001000100000011100010010000001110000011011110110111001101101011011000010000001101011011010100110100101100100011000110110001001100001 N
b10001 P
0R
b10010 U
b1 W
0X
b0 c
b0 d
0e
b1 f
bx p
#23000
0)
b1110100 ,
b10010 2
0;
b1110100 =
#23500
1)
b11000 1
1;
b1110100011100110111001000100000011100010010000001110000011011110110111001101101011011000010000001101011011010100110100101100100011000110110001001100001 E
b10010 G
b1110100011100110111001000100000011100010010000001110000011011110110111001101101011011000010000001101011011010100110100101100100011000110110001001100001 N
b10010 P
0R
b10011 U
b1 W
0X
b0 c
b0 d
0e
b1 f
bx p
#24000
0)
b1110101 ,
b10011 2
0;
b1110101 =
#24500
1)
b11001 1
1;
b111010101110100011100110111001000100000011100010010000001110000011011110110111001101101011011000010000001101011011010100110100101100100011000110110001001100001 E
b10011 G
b111010101110100011100110111001000100000011100010010000001110000011011110110111001101101011011000010000001101011011010100110100101100100011000110110001001100001 N
b10011 P
0R
b10100 U
b1 W
0X
b0 c
b0 d
0e
b1 f
bx p
#25000
0)
b1110110 ,
b10100 2
0;
b1110110 =
#25500
1)
b11010 1
1;
b11101100111010101110100011100110111001000100000011100010010000001110000011011110110111001101101011011000010000001101011011010100110100101100100011000110110001001100001 E
b10100 G
b11101100111010101110100011100110111001000100000011100010010000001110000011011110110111001101101011011000010000001101011011010100110100101100100011000110110001001100001 N
b10100 P
0R
b10101 U
b1 W
0X
b0 c
b0 d
0e
b1 f
bx p
#26000
b10100 "
0)
b110001 ,
0-
1.
b0 2
b0 3
04
0;
b110001 =
0>
1?
1C
1D
#26500
1)
b11011 1
1;
b110001 F
b110001 O
b0 Q
0R
b1 V
b1 W
0X
b0 c
b0 d
0e
b1 f
bx p
#27000
0)
b110010 ,
b1 2
0;
b110010 =
#27500
1)
b11100 1
1;
b11001000110001 F
b1 H
b11001000110001 O
b1 Q
0R
b10 V
b1 W
0X
b0 c
b0 d
0e
b1 f
bx p
#28000
0)
b110011 ,
b10 2
0;
b110011 =
#28500
1)
b11101 1
1;
b1100110011001000110001 F
b10 H
b1100110011001000110001 O
b10 Q
0R
b11 V
b1 W
0X
b0 c
b0 d
0e
b1 f
bx p
#29000
0)
b110100 ,
b11 2
0;
b110100 =
#29500
1)
b11110 1
1;
b110100001100110011001000110001 F
b11 H
b110100001100110011001000110001 O
b11 Q
0R
b100 V
b1 W
0X
b0 c
b0 d
0e
b1 f
bx p
#30000
0)
b110001 ,
b100 2
0;
b110001 =
#30500
1)
b11111 1
1;
b11000100110100001100110011001000110001 F
b100 H
b11000100110100001100110011001000110001 O
b100 Q
0R
b101 V
b1 W
0X
b0 c
b0 d
0e
b1 f
bx p
#31000
0)
b110010 ,
b101 2
0;
b110010 =
#31500
1)
b100000 1
1;
b1100100011000100110100001100110011001000110001 F
b101 H
b1100100011000100110100001100110011001000110001 O
b101 Q
0R
b110 V
b1 W
0X
b0 c
b0 d
0e
b1 f
bx p
#32000
0)
b110011 ,
b110 2
0;
b110011 =
#32500
1)
b100001 1
1;
b110011001100100011000100110100001100110011001000110001 F
b110 H
b110011001100100011000100110100001100110011001000110001 O
b110 Q
0R
b111 V
b1 W
0X
b0 c
b0 d
0e
b1 f
bx p
#33000
0)
b110001 ,
b111 2
0;
b110001 =
#33500
1)
b100010 1
1;
b11000100110011001100100011000100110100001100110011001000110001 F
b111 H
b11000100110011001100100011000100110100001100110011001000110001 O
b111 Q
0R
b0 V
b1 W
0X
b0 c
b0 d
0e
b1 f
bx p
#34000
0)
0.
16
0;
0?
0C
0D
#34500
1)
b100011 1
1;
b0 U
b0 V
b10 W
1X
1`
b0 c
b0 d
0e
b1 f
b10 g
bx p
#35000
0)
0;
#35500
1)
b100100 1
1;
b0 U
b0 V
b0 c
b0 d
0e
b10 f
b10 g
bx p
#36000
0)
0;
#36500
1)
b100101 1
1;
b0 U
b0 V
b0 a
b1 c
b0 d
b10 f
bx p
#37000
0)
0;
#37500
1)
b100110 1
1;
b0 U
b0 V
b0 a
b10 c
b0 d
b10 f
bx p
#38000
0)
0;
#38500
1)
b100111 1
1;
b0 U
b0 V
b0 a
b11 c
b0 d
b10 f
bx p
#39000
0)
0;
#39500
1)
b101000 1
1;
b0 U
b0 V
b0 a
b100 c
b0 d
b10 f
bx p
#40000
0)
0;
#40500
1)
b101001 1
1;
b1000000000000 J
b0 U
b0 V
b1000000000000 a
b101 c
b1 d
b10 f
bx p
#41000
0)
0;
#41500
1)
b101010 1
1;
b10001000000000000 J
b0 U
b0 V
b10001000000000000 a
b110 c
b10 d
b10 f
bx p
#42000
0)
0;
