src/PE_slave.v
`define BYTE 8
`define NUM_SLAVE 4
`define MAX_STRING 32
  `define MAX_STR_ADD 5
`define MAX_PATTERN 8
  `define MAX_PAT_ADD 3

module pe_slave(clk, reset, str_input, pat_input, input_valid, start_idx, process_2idx, output_valid, match, match_idx);
input clk;
input reset;
input [`MAX_STRING * `BYTE - 1 : 0] str_input;
input [`MAX_PATTERN * `BYTE - 1 : 0] pat_input;
input input_valid;
input [`MAX_STR_ADD - 1 : 0] start_idx;
input [`MAX_STR_ADD - 1 : 0] process_2idx;

output reg output_valid;
output reg match;
output reg [`MAX_STR_ADD - 1 : 0] match_idx;
//---------------------input/output---------------------//

localparam NUM_STATE = 4;
reg [NUM_STATE - 1 : 0] current_st;
reg [NUM_STATE - 1 : 0] next_st;
  localparam IDLE_ST = 'b0001;
  localparam PRE_ST = 'b0010;
  localparam COM_ST = 'b0100;
  localparam DONE_ST = 'b1000;
//---------------------FSM PARM---------------------//

reg signed [`MAX_PAT_ADD - 1 : 0] kmp_map [0 : `MAX_PATTERN - 1];


always@(posedge clk)
begin
  if(reset) current_st <= IDLE_ST;
  else current_st <= next_st;
end

always@(*)
begin
  case(currnet_st)
  IDLE_ST: if(input_valid) next_st = PRE_ST;
  endcase
end



endmodule

src/shared_memory.v
`define BYTE 8
`define NUM_SLAVE 4
`define MAX_STRING 32
  `define MAX_STR_ADD 5
`define MAX_PATTERN 8
  `define MAX_PAT_ADD 3

module shared_memory(clk, reset, w_data, write, w_sel, str_reg, pat_reg, str_last_idx, pat_last_idx, valid);
  input clk;
  input reset;
  input [`BYTE - 1:0] w_data;
  input write;
  input w_sel;

  output reg [`MAX_STRING * `BYTE - 1 : 0] str_reg;
  output reg [`MAX_PATTERN * `BYTE - 1 : 0] pat_reg;
  output reg [`MAX_STR_ADD - 1: 0] str_last_idx;
  output reg [`MAX_PAT_ADD - 1: 0] pat_last_idx;
  output reg valid;
//---------------------input/output---------------------//

  integer i, j;
  parameter sel_str_reg = 0;
  parameter sel_pat_reg = 1;

  reg [`MAX_STR_ADD - 1 : 0] s_index;
  reg [`MAX_PAT_ADD - 1 : 0] p_index;
  reg [2:0] active;
    localparam NON_READ = 0;
    localparam READING = 1;
    localparam DONE = 2;


  always@(posedge clk)
  begin
      if(reset)
      begin
        s_index <= 0;
        p_index <= 0;
        str_last_idx <= 0;
        pat_last_idx <= 0;
        active <= 0;
        valid <= 0;

        for(i = 0; i < (`MAX_STRING * `BYTE); i = i + 1)
        begin
          str_reg[i] <= 0;
        end

        for(j = 0; j < (`MAX_PATTERN * `BYTE); j = j + 1)
        begin
          pat_reg[j] <= 0;
        end
      end
      
      else if(write)
      begin
        active <= READING;
        valid <= 0;
        case(w_sel)
          sel_str_reg : begin str_reg[s_index * `BYTE +: `BYTE] <= w_data; s_index <= s_index + 1; str_last_idx <= s_index; end
          sel_pat_reg : begin pat_reg[p_index * `BYTE +: `BYTE] <= w_data; p_index <= p_index + 1; pat_last_idx <= p_index; end
        endcase
      end

      else
      begin
        if(active == READING) begin active <= DONE; valid <= 1; end
        else active <= NON_READ;

        s_index <= 0;
        p_index <= 0;
      end
end

endmodule

src/SME.v
module SME(
  input clk,
  input reset,
  input [7:0] chardata,
  input isstring,
  input ispattern,
  output reg valid,
  output reg match,
  output reg [4:0] match_index
  );

  wire write;
  assign write = (ispattern || isstring)? 1:0;
  wire w_sel;
  assign w_sel = (ispattern)? 1:0;

  wire [255:0]str;
  wire [63:0] pat;
  wire [5:0] str_last_index;
  wire [3:0] pat_last_index;
  wire input_valid;
  shared_memory s1(.clk(clk), .reset(reset), .w_data(chardata), .write(write), .w_sel(w_sel), .str_reg(str), .pat_reg(pat), .str_last_idx(str_last_index), .pat_last_idx(pat_last_index), .valid(input_valid));

  wire o_valid;
  wire s_match;
  wire [5:0] s_match_idx;
  pe_slave ps1(.clk(clk), .reset(reset), .str_input(str), .pat_input(pat), .input_valid(input_valid), .start_idx(0), .process_2idx(str_last_index), .output_valid(o_valid), .match(s_match), .match_idx(s_match_idx));



endmodule

test_bench/sme_tb.sv
`timescale 1ns/10ps
`define CYCLE      20.0  
`define SDFFILE    "./SME_syn.sdf"
`define End_CYCLE  1000000
`define PAT        "test_pattern1.txt"
module testfixture();

integer linedata;
integer char_count;
//reg [128:0] data;
string data;
string strnum;
string patnum;
string strdata;
string goldmatch_s;
string goldmatch_index_s;

reg clk = 0;
wire valid;
reg reset =0;
reg [7:0] chardata;
reg isstring=0;
reg ispattern=0;
wire match;
wire [4:0] match_index;
SME u_SME (.clk(clk),
           .reset(reset),
           .chardata(chardata),
           .isstring(isstring),
           .ispattern(ispattern),
           .valid(valid),
           .match(match),
           .match_index(match_index));

`ifdef SDF
    initial $sdf_annotate(`SDFFILE, u_SME);
`endif

always begin #(`CYCLE/2) clk = ~clk; end
/*
initial begin
    $fsdbDumpfile("SME.fsdb");
    $fsdbDumpvars;
    $fsdbDumpMDA;
end
*/
//initial begin
//    $dumpfile("SME.vcd");
//    $dumpvars;
//end

initial begin
    $display("----------------------");
    $display("-- Simulation Start --");
    $display("----------------------");
    @(posedge clk); #1; reset = 1'b1; 
    #(`CYCLE*2);  
    @(posedge clk); #1;   reset = 1'b0;
end

reg [22:0] cycle=0;

always @(posedge clk) begin
    cycle=cycle+1;
    if (cycle > `End_CYCLE) begin
        $display("--------------------------------------------------");
        $display("-- Failed waiting valid signal, Simulation STOP --");
        $display("--------------------------------------------------");
        $fclose(linedata);
        $finish;
    end
end

initial begin
    linedata = $fopen(`PAT,"r");
    if (linedata == 0) begin
        $display ("pattern handle null");
        $finish;
    end
end

integer strindex;
reg [7:0] goldmatch_index;
reg  goldmatch;
reg  valid_reg;
reg wait_valid;
reg  getmatch;
reg [7:0] getmatch_index;
always @(posedge clk) begin
    valid_reg = valid;
end

integer score=0;
integer allpass=1;
always @(negedge clk) begin
    if (reset) begin
        wait_valid=0;
    end
    else begin
        if (wait_valid==1 && valid ==1) begin
            wait_valid=0;
            getmatch=match;
            getmatch_index=match_index;
            //$display ("       string/pattern = %s/%s",strnum,patnum);
            if(goldmatch==1)begin
                if(getmatch == goldmatch) begin
                    score++;
                    if(getmatch_index==goldmatch_index) begin
                        score=score+2;
                        //colordisplay(cycle,goldmatch,goldmatch_index,getmatch,getmatch_index,3);
                        $display ("       cycle %2h, expect(%h,%h) , get(%h,%h) >> Pass",cycle,goldmatch,goldmatch_index,getmatch,getmatch_index);
                    end
                    else begin 
                        allpass=0;
                        //colordisplay(cycle,goldmatch,goldmatch_index,getmatch,getmatch_index,2);
                        $display ("       cycle %2h, expect(%h,%h) , get(%h,%h) >> Wrong index",cycle,goldmatch,goldmatch_index,getmatch,getmatch_index);
                    end
                end
                else begin
                    allpass=0;
                    //colordisplay(cycle,goldmatch,goldmatch_index,getmatch,getmatch_index,0);
                    $display ("       cycle %2h, expect(%h,%h) , get(%h,%h) >> Fail",cycle,goldmatch,goldmatch_index,getmatch,getmatch_index);
                end
            end
            else begin
                if(getmatch == goldmatch) begin
                    score++;
                    //colordisplay(cycle,goldmatch,goldmatch_index,getmatch,getmatch_index,3);
                    $display ("       cycle %2h, expect(%h,--) , get(%h,--) >> Pass",cycle, goldmatch,getmatch);
                end
                else begin
                    allpass=0;
                    //colordisplay(cycle,goldmatch,goldmatch_index,getmatch,getmatch_index,1);
                    $display ("       cycle %2h, expect(%h,--) , get(%h,--) >> Fail",cycle, goldmatch,getmatch);
                end
            end
        //$display ("       score = %d",score);
        end
    end
end

always @(negedge clk ) begin
    if (reset) begin
        isstring=0;
        ispattern=0;
        valid_reg=0;
    end 
    else begin
        if (strindex==strdata.len()-1) begin
            isstring=0;
            if(ispattern==1) wait_valid=1;
            ispattern=0;
        end
        if (wait_valid == 1'b0) begin
            if (strindex<strdata.len()-1) begin
                strindex=strindex+1;
                chardata = strdata.getc(strindex);
                //$display("%h %s,%h",cycle,chardata,chardata);
            end 
            else begin
                if (!$feof(linedata))begin
                    char_count = $fgets (data, linedata);
                    if (char_count !== 0) begin
                        if(data.substr(0,3) == "str:") begin
                            isstring=1; 
                            strindex=0;
                            strnum = data.substr(4,4);
                            strdata = data.substr(6,data.len()-2);
                            $display("  __________________________________________________________");
                            $display("  == String %s  \"%s\"", strnum, strdata);
                            chardata = strdata.getc(strindex);
                            //$display("%h %s,%h",cycle,chardata,chardata);
                        end 
                        else begin
                            if(data.substr(0,3) == "pat:") begin
                                ispattern=1; 
                                strindex=0;
                                patnum = data.substr(4,4);
                                goldmatch_s = data.substr(6,6);
                                goldmatch = goldmatch_s.atoi();
                                goldmatch_index_s = data.substr(8,9);
                                goldmatch_index = goldmatch_index_s.atoi();
                                strdata = data.substr(11,data.len()-2);
                                //$display("==== Pattern__%s__%b__%2d__%s", patnum, goldmatch,goldmatch_index,strdata);
                                $display("  -- Pattern %s  \"%s\"", patnum, strdata);
                                chardata = strdata.getc(strindex);
                                //$display("%h %s,%h",cycle,chardata,chardata);
                            end
                        end
                    end
                end
                else begin
                    $display("----------------------------------");
                    if(allpass == 1 && score >1)
                    $display("-- Simulation finish, ALL PASS  --");
                    else
                    $display("-- Simulation finish            --");
                    $display("-- cycle =%3d , Score =%2d       --",cycle, score);
                    $display("----------------------------------");
                    $fclose(linedata);
                    $finish;
                end
            end
        end // if wait_valid == 0
    end
end
endmodule

task colordisplay;
    input [12:0] cycle;
    input goldmatch;
    input [7:0] goldmatchindex;
    input getmatch;
    input [7:0] getmatchindex;
    input [1:0]pass; 
    begin
        $write ("       cycle %2h, expect(%h,%h) , get(",cycle,goldmatch,goldmatchindex);
        case(pass)
            2'd0: begin   // expect match , failed
                $write("%c[1;31m",27);
                $write ("%h,%h",getmatch,getmatchindex);
                $write("%c[0m",27);
                $write (") >> Fail\n");

                  end
            2'd1: begin   // expect unmatch, failed
                $write("%c[1;31m",27);
                $write ("%h",getmatch);
                $write ("%c[0m",27);
                $write (",%h) >> Fail\n",getmatchindex);

                  end
            2'd2: begin  // expect match, wrong index
                $write ("%h,",getmatch);
                $write("%c[1;31m",27);
                $write ("%h",getmatchindex);
                $write("%c[0m",27);
                $write (") >> Wrong index\n");

                  end
            2'd3: begin // both match or unmatch, passed
                $write ("%h,%h",getmatch,getmatchindex);
                $write (") >> Pass\n");

                  end
        endcase
    end
endtask

vivado_project/SME_parallel.sim/sim_1/behav/xsim/SME.vcd
$date
   Fri Dec  4 12:58:42 2020
$end
$version
  2019.1
$end
$timescale
  1ps
$end
$scope module testfixture $end
$var integer 32 ! linedata $end
$var integer 32 " char_count $end
$var reg 32 # data $end
$var reg 32 $ strnum $end
$var reg 32 % patnum $end
$var reg 32 & strdata $end
$var reg 32 ' goldmatch_s $end
$var reg 32 ( goldmatch_index_s $end
$var reg 1 ) clk $end
$var wire 1 * valid $end
$var reg 1 + reset $end
$var reg 8 , chardata [7:0] $end
$var reg 1 - isstring $end
$var reg 1 . ispattern $end
$var wire 1 / match $end
$var wire 5 0 match_index [4:0] $end
$var reg 23 1 cycle [22:0] $end
$var integer 32 2 strindex $end
$var reg 8 3 goldmatch_index [7:0] $end
$var reg 1 4 goldmatch $end
$var reg 1 5 valid_reg $end
$var reg 1 6 wait_valid $end
$var reg 1 7 getmatch $end
$var reg 8 8 getmatch_index [7:0] $end
$var integer 32 9 score $end
$var integer 32 : allpass $end
$scope module u_SME $end
$var wire 1 ; clk $end
$var wire 1 < reset $end
$var wire 8 = chardata [7:0] $end
$var wire 1 > isstring $end
$var wire 1 ? ispattern $end
$var reg 1 @ valid $end
$var reg 1 A match $end
$var reg 5 B match_index [4:0] $end
$var wire 1 C write $end
$var wire 1 D w_sel $end
$var wire 256 E str [255:0] $end
$var wire 64 F pat [63:0] $end
$var wire 6 G str_last_index [5:0] $end
$var wire 4 H pat_last_index [3:0] $end
$var wire 1 I input_valid $end
$var wire 1 J o_valid $end
$var wire 1 K s_match $end
$var wire 6 L s_match_idx [5:0] $end
$scope module s1 $end
$var wire 1 ; clk $end
$var wire 1 < reset $end
$var wire 8 = w_data [7:0] $end
$var wire 1 C write $end
$var wire 1 D w_sel $end
$var reg 256 M str_reg [255:0] $end
$var reg 64 N pat_reg [63:0] $end
$var reg 5 O str_last_idx [4:0] $end
$var reg 3 P pat_last_idx [2:0] $end
$var reg 1 Q valid $end
$var integer 32 R i $end
$var integer 32 S j $end
$var reg 5 T s_index [4:0] $end
$var reg 3 U p_index [2:0] $end
$var reg 3 V active [2:0] $end
$var parameter 32 W sel_str_reg [31:0] $end
$var parameter 32 X sel_pat_reg [31:0] $end
$var parameter 32 Y NON_READ [31:0] $end
$var parameter 32 Z READING [31:0] $end
$var parameter 32 [ DONE [31:0] $end
$upscope $end
$scope module ps1 $end
$var wire 1 ; clk $end
$var wire 1 < reset $end
$var wire 256 E str_input [255:0] $end
$var wire 64 F pat_input [63:0] $end
$var wire 1 I input_valid $end
$var wire 5 \ start_idx [4:0] $end
$var wire 5 ] process_2idx [4:0] $end
$var reg 1 ^ output_valid $end
$var reg 1 _ match $end
$var reg 5 ` match_idx [4:0] $end
$var reg 4 a current_st [3:0] $end
$var reg 4 b next_st [3:0] $end
$var parameter 32 c NUM_STATE [31:0] $end
$var parameter 32 d IDLE_ST [31:0] $end
$var parameter 32 e PRE_ST [31:0] $end
$var parameter 32 f COM_ST [31:0] $end
$var parameter 32 g DONE_ST [31:0] $end
$upscope $end
$upscope $end
$upscope $end
$enddefinitions $end
#0
$dumpvars
b11111111111111111011000111100000 !
bx "
b0 #
b0 $
b0 %
b0 &
b0 '
b0 (
0)
x*
0+
bx ,
0-
0.
x/
bx 0
b0 1
bx 2
bx 3
x4
x5
x6
x7
bx 8
b0 9
b1 :
0;
0<
bx =
0>
0?
x@
xA
bx B
0C
0D
bx E
bx F
bzxxxxx G
bzxxx H
xI
xJ
xK
bzxxxxx L
bx M
bx N
bx O
bx P
xQ
bx R
bx S
bx T
bx U
bx V
b0 W
b1 X
b0 Y
b1 Z
b10 [
b0 \
bx ]
x^
x_
bx `
bx a
bx b
b100 c
b1 d
b10 e
b100 f
b1000 g
$end
#500
1)
b1 1
1;
b0 T
b0 U
b0 V
#1000
0)
0;
#1500
1)
1+
b10 1
1;
1<
b0 E
b0 F
bz00000 G
bz000 H
0I
b0 M
b0 N
b0 O
b0 P
0Q
b100000000 R
b1000000 S
b0 T
b0 U
b0 V
b0 ]
#2000
0)
05
06
0;
#2500
1)
b11 1
x5
1;
b0 M
b0 N
b0 O
b0 P
0Q
b100000000 R
b1000000 S
b0 T
b0 U
b0 V
#3000
0)
05
0;
#3500
1)
b100 1
x5
1;
b0 M
b0 N
b0 O
b0 P
0Q
b100000000 R
b1000000 S
b0 T
b0 U
b0 V
#4000
0)
05
0;
#4500
1)
0+
b101 1
x5
1;
0<
b0 T
b0 U
b0 V
#5000
b11100 "
0)
b1100001 ,
1-
b0 2
0;
b1100001 =
1>
1C
#5500
1)
b110 1
1;
b1100001 E
b1100001 M
b0 O
0Q
b1 T
b1 V
#6000
0)
b1100010 ,
b1 2
0;
b1100010 =
#6500
1)
b111 1
1;
b110001001100001 E
bz00001 G
b110001001100001 M
b1 O
0Q
b10 T
b1 V
b1 ]
#7000
0)
b1100011 ,
b10 2
0;
b1100011 =
#7500
1)
b1000 1
1;
b11000110110001001100001 E
bz00010 G
b11000110110001001100001 M
b10 O
0Q
b11 T
b1 V
b10 ]
#8000
0)
b1100100 ,
b11 2
0;
b1100100 =
#8500
1)
b1001 1
1;
b1100100011000110110001001100001 E
bz00011 G
b1100100011000110110001001100001 M
b11 O
0Q
b100 T
b1 V
b11 ]
#9000
0)
b1101001 ,
b100 2
0;
b1101001 =
#9500
1)
b1010 1
1;
b110100101100100011000110110001001100001 E
bz00100 G
b110100101100100011000110110001001100001 M
b100 O
0Q
b101 T
b1 V
b100 ]
#10000
0)
b1101010 ,
b101 2
0;
b1101010 =
#10500
1)
b1011 1
1;
b11010100110100101100100011000110110001001100001 E
bz00101 G
b11010100110100101100100011000110110001001100001 M
b101 O
0Q
b110 T
b1 V
b101 ]
#11000
0)
b1101011 ,
b110 2
0;
b1101011 =
#11500
1)
b1100 1
1;
b1101011011010100110100101100100011000110110001001100001 E
bz00110 G
b1101011011010100110100101100100011000110110001001100001 M
b110 O
0Q
b111 T
b1 V
b110 ]
#12000
0)
b100000 ,
b111 2
0;
b100000 =
#12500
1)
b1101 1
1;
b10000001101011011010100110100101100100011000110110001001100001 E
bz00111 G
b10000001101011011010100110100101100100011000110110001001100001 M
b111 O
0Q
b1000 T
b1 V
b111 ]
#13000
0)
b1101100 ,
b1000 2
0;
b1101100 =
#13500
1)
b1110 1
1;
b11011000010000001101011011010100110100101100100011000110110001001100001 E
bz01000 G
b11011000010000001101011011010100110100101100100011000110110001001100001 M
b1000 O
0Q
b1001 T
b1 V
b1000 ]
#14000
0)
b1101101 ,
b1001 2
0;
b1101101 =
#14500
1)
b1111 1
1;
b1101101011011000010000001101011011010100110100101100100011000110110001001100001 E
bz01001 G
b1101101011011000010000001101011011010100110100101100100011000110110001001100001 M
b1001 O
0Q
b1010 T
b1 V
b1001 ]
#15000
0)
b1101110 ,
b1010 2
0;
b1101110 =
#15500
1)
b10000 1
1;
b110111001101101011011000010000001101011011010100110100101100100011000110110001001100001 E
bz01010 G
b110111001101101011011000010000001101011011010100110100101100100011000110110001001100001 M
b1010 O
0Q
b1011 T
b1 V
b1010 ]
#16000
0)
b1101111 ,
b1011 2
0;
b1101111 =
#16500
1)
b10001 1
1;
b11011110110111001101101011011000010000001101011011010100110100101100100011000110110001001100001 E
bz01011 G
b11011110110111001101101011011000010000001101011011010100110100101100100011000110110001001100001 M
b1011 O
0Q
b1100 T
b1 V
b1011 ]
#17000
0)
b1110000 ,
b1100 2
0;
b1110000 =
#17500
1)
b10010 1
1;
b1110000011011110110111001101101011011000010000001101011011010100110100101100100011000110110001001100001 E
bz01100 G
b1110000011011110110111001101101011011000010000001101011011010100110100101100100011000110110001001100001 M
b1100 O
0Q
b1101 T
b1 V
b1100 ]
#18000
0)
b100000 ,
b1101 2
0;
b100000 =
#18500
1)
b10011 1
1;
b10000001110000011011110110111001101101011011000010000001101011011010100110100101100100011000110110001001100001 E
bz01101 G
b10000001110000011011110110111001101101011011000010000001101011011010100110100101100100011000110110001001100001 M
b1101 O
0Q
b1110 T
b1 V
b1101 ]
#19000
0)
b1110001 ,
b1110 2
0;
b1110001 =
#19500
1)
b10100 1
1;
b11100010010000001110000011011110110111001101101011011000010000001101011011010100110100101100100011000110110001001100001 E
bz01110 G
b11100010010000001110000011011110110111001101101011011000010000001101011011010100110100101100100011000110110001001100001 M
b1110 O
0Q
b1111 T
b1 V
b1110 ]
#20000
0)
b100000 ,
b1111 2
0;
b100000 =
#20500
1)
b10101 1
1;
b100000011100010010000001110000011011110110111001101101011011000010000001101011011010100110100101100100011000110110001001100001 E
bz01111 G
b100000011100010010000001110000011011110110111001101101011011000010000001101011011010100110100101100100011000110110001001100001 M
b1111 O
0Q
b10000 T
b1 V
b1111 ]
#21000
0)
b1110010 ,
b10000 2
0;
b1110010 =
#21500
1)
b10110 1
1;
b111001000100000011100010010000001110000011011110110111001101101011011000010000001101011011010100110100101100100011000110110001001100001 E
bz10000 G
b111001000100000011100010010000001110000011011110110111001101101011011000010000001101011011010100110100101100100011000110110001001100001 M
b10000 O
0Q
b10001 T
b1 V
b10000 ]
#22000
0)
b1110011 ,
b10001 2
0;
b1110011 =
#22500
1)
b10111 1
1;
b11100110111001000100000011100010010000001110000011011110110111001101101011011000010000001101011011010100110100101100100011000110110001001100001 E
bz10001 G
b11100110111001000100000011100010010000001110000011011110110111001101101011011000010000001101011011010100110100101100100011000110110001001100001 M
b10001 O
0Q
b10010 T
b1 V
b10001 ]
#23000
0)
b1110100 ,
b10010 2
0;
b1110100 =
#23500
1)
b11000 1
1;
b1110100011100110111001000100000011100010010000001110000011011110110111001101101011011000010000001101011011010100110100101100100011000110110001001100001 E
bz10010 G
b1110100011100110111001000100000011100010010000001110000011011110110111001101101011011000010000001101011011010100110100101100100011000110110001001100001 M
b10010 O
0Q
b10011 T
b1 V
b10010 ]
#24000
0)
b1110101 ,
b10011 2
0;
b1110101 =
#24500
1)
b11001 1
1;
b111010101110100011100110111001000100000011100010010000001110000011011110110111001101101011011000010000001101011011010100110100101100100011000110110001001100001 E
bz10011 G
b111010101110100011100110111001000100000011100010010000001110000011011110110111001101101011011000010000001101011011010100110100101100100011000110110001001100001 M
b10011 O
0Q
b10100 T
b1 V
b10011 ]
#25000
0)
b1110110 ,
b10100 2
0;
b1110110 =
#25500
1)
b11010 1
1;
b11101100111010101110100011100110111001000100000011100010010000001110000011011110110111001101101011011000010000001101011011010100110100101100100011000110110001001100001 E
bz10100 G
b11101100111010101110100011100110111001000100000011100010010000001110000011011110110111001101101011011000010000001101011011010100110100101100100011000110110001001100001 M
b10100 O
0Q
b10101 T
b1 V
b10100 ]
#26000
b10000 "
0)
b110001 ,
0-
1.
b0 2
b0 3
04
0;
b110001 =
0>
1?
1C
1D
#26500
1)
b11011 1
1;
b110001 F
b110001 N
b0 P
0Q
b1 U
b1 V
#27000
0)
b110010 ,
b1 2
0;
b110010 =
#27500
1)
b11100 1
1;
b11001000110001 F
bz001 H
b11001000110001 N
b1 P
0Q
b10 U
b1 V
#28000
0)
b110011 ,
b10 2
0;
b110011 =
#28500
1)
b11101 1
1;
b1100110011001000110001 F
bz010 H
b1100110011001000110001 N
b10 P
0Q
b11 U
b1 V
#29000
0)
b110100 ,
b11 2
0;
b110100 =
#29500
1)
b11110 1
1;
b110100001100110011001000110001 F
bz011 H
b110100001100110011001000110001 N
b11 P
0Q
b100 U
b1 V
#30000
0)
0.
16
0;
0?
0C
0D
#30500
1)
b11111 1
1;
1I
1Q
b0 T
b0 U
b10 V
#31000
0)
0;
#31500
1)
b100000 1
1;
b0 T
b0 U
b0 V
#32000
0)
0;
#32500
1)
b100001 1
1;
b0 T
b0 U
b0 V
#33000
0)
0;
#33500
1)
b100010 1
1;
b0 T
b0 U
b0 V
#34000
0)
0;
#34500
1)
b100011 1
1;
b0 T
b0 U
b0 V
#35000
0)
0;
#35500
1)
b100100 1
1;
b0 T
b0 U
b0 V
#36000
0)
0;
#36500
1)
b100101 1
1;
b0 T
b0 U
b0 V
#37000
0)
0;
#37500
1)
b100110 1
1;
b0 T
b0 U
b0 V
#38000
0)
0;
#38500
1)
b100111 1
1;
b0 T
b0 U
b0 V
#39000
0)
0;
#39500
1)
b101000 1
1;
b0 T
b0 U
b0 V
#40000
0)
0;
#40500
1)
b101001 1
1;
b0 T
b0 U
b0 V
#41000
0)
0;
#41500
1)
b101010 1
1;
b0 T
b0 U
b0 V
#42000
0)
0;
#42500
1)
b101011 1
1;
b0 T
b0 U
b0 V
#43000
0)
0;
#43500
1)
b101100 1
1;
b0 T
b0 U
b0 V
#44000
0)
0;
#44500
1)
b101101 1
1;
b0 T
b0 U
b0 V
#45000
0)
0;
#45500
1)
b101110 1
1;
b0 T
b0 U
b0 V
#46000
0)
0;
#46500
1)
b101111 1
1;
b0 T
b0 U
b0 V
#47000
0)
0;
#47500
1)
b110000 1
1;
b0 T
b0 U
b0 V
#48000
0)
0;
#48500
1)
b110001 1
1;
b0 T
b0 U
b0 V
#49000
0)
0;
#49500
1)
b110010 1
1;
b0 T
b0 U
b0 V
#50000
0)
0;
#50500
1)
b110011 1
1;
b0 T
b0 U
b0 V
#51000
0)
0;
#51500
1)
b110100 1
1;
b0 T
b0 U
b0 V
#52000
0)
0;
#52500
1)
b110101 1
1;
b0 T
b0 U
b0 V
#53000
0)
0;
#53500
1)
b110110 1
1;
b0 T
b0 U
b0 V
#54000
0)
0;
#54500
1)
b110111 1
1;
b0 T
b0 U
b0 V
#55000
0)
0;
#55500
1)
b111000 1
1;
b0 T
b0 U
b0 V
#56000
0)
0;
#56500
1)
b111001 1
1;
b0 T
b0 U
b0 V
#57000
0)
0;
#57500
1)
b111010 1
1;
b0 T
b0 U
b0 V
#58000
0)
0;
#58500
1)
b111011 1
1;
b0 T
b0 U
b0 V
#59000
0)
0;
#59500
1)
b111100 1
1;
b0 T
b0 U
b0 V
#60000
0)
0;
#60500
1)
b111101 1
1;
b0 T
b0 U
b0 V
#61000
0)
0;
#61500
1)
b111110 1
1;
b0 T
b0 U
b0 V
#62000
0)
0;
#62500
1)
b111111 1
1;
b0 T
b0 U
b0 V
#63000
0)
0;
#63500
1)
b1000000 1
1;
b0 T
b0 U
b0 V
#64000
0)
0;
#64500
1)
b1000001 1
1;
b0 T
b0 U
b0 V
#65000
0)
0;
#65500
1)
b1000010 1
1;
b0 T
b0 U
b0 V
#66000
0)
0;
#66500
1)
b1000011 1
1;
b0 T
b0 U
b0 V
#67000
0)
0;
#67500
1)
b1000100 1
1;
b0 T
b0 U
b0 V
#68000
0)
0;
#68500
1)
b1000101 1
1;
b0 T
b0 U
b0 V
#69000
0)
0;
#69500
1)
b1000110 1
1;
b0 T
b0 U
b0 V
#70000
0)
0;
#70500
1)
b1000111 1
1;
b0 T
b0 U
b0 V
#71000
0)
0;
#71500
1)
b1001000 1
1;
b0 T
b0 U
b0 V
#72000
0)
0;
#72500
1)
b1001001 1
1;
b0 T
b0 U
b0 V
#73000
0)
0;
#73500
1)
b1001010 1
1;
b0 T
b0 U
b0 V
#74000
0)
0;
#74500
1)
b1001011 1
1;
b0 T
b0 U
b0 V
#75000
0)
0;
#75500
1)
b1001100 1
1;
b0 T
b0 U
b0 V
#76000
0)
0;
#76500
1)
b1001101 1
1;
b0 T
b0 U
b0 V
#77000
0)
0;
#77500
1)
b1001110 1
1;
b0 T
b0 U
b0 V
#78000
0)
0;
#78500
1)
b1001111 1
1;
b0 T
b0 U
b0 V
#79000
0)
0;
#79500
1)
b1010000 1
1;
b0 T
b0 U
b0 V
#80000
0)
0;
#80500
1)
b1010001 1
1;
b0 T
b0 U
b0 V
#81000
0)
0;
#81500
1)
b1010010 1
1;
b0 T
b0 U
b0 V
#82000
0)
0;
#82500
1)
b1010011 1
1;
b0 T
b0 U
b0 V
#83000
0)
0;
#83500
1)
b1010100 1
1;
b0 T
b0 U
b0 V
#84000
0)
0;
#84500
1)
b1010101 1
1;
b0 T
b0 U
b0 V
#85000
0)
0;
#85500
1)
b1010110 1
1;
b0 T
b0 U
b0 V
#86000
0)
0;
#86500
1)
b1010111 1
1;
b0 T
b0 U
b0 V
#87000
0)
0;
#87500
1)
b1011000 1
1;
b0 T
b0 U
b0 V
#88000
0)
0;
#88500
1)
b1011001 1
1;
b0 T
b0 U
b0 V
#89000
0)
0;
#89500
1)
b1011010 1
1;
b0 T
b0 U
b0 V
#90000
0)
0;
#90500
1)
b1011011 1
1;
b0 T
b0 U
b0 V
#91000
0)
0;
#91500
1)
b1011100 1
1;
b0 T
b0 U
b0 V
#92000
0)
0;
#92500
1)
b1011101 1
1;
b0 T
b0 U
b0 V
#93000
0)
0;
#93500
1)
b1011110 1
1;
b0 T
b0 U
b0 V
#94000
0)
0;
#94500
1)
b1011111 1
1;
b0 T
b0 U
b0 V
#95000
0)
0;
#95500
1)
b1100000 1
1;
b0 T
b0 U
b0 V
#96000
0)
0;
#96500
1)
b1100001 1
1;
b0 T
b0 U
b0 V
#97000
0)
0;
#97500
1)
b1100010 1
1;
b0 T
b0 U
b0 V
#98000
0)
0;
#98500
1)
b1100011 1
1;
b0 T
b0 U
b0 V
#99000
0)
0;
#99500
1)
b1100100 1
1;
b0 T
b0 U
b0 V
#100000
0)
0;
#100500
1)
b1100101 1
1;
b0 T
b0 U
b0 V
#101000
0)
0;
#101500
1)
b1100110 1
1;
b0 T
b0 U
b0 V
#102000
0)
0;
#102500
1)
b1100111 1
1;
b0 T
b0 U
b0 V
#103000
0)
0;
#103500
1)
b1101000 1
1;
b0 T
b0 U
b0 V
#104000
0)
0;
#104500
1)
b1101001 1
1;
b0 T
b0 U
b0 V
#105000
0)
0;
#105500
1)
b1101010 1
1;
b0 T
b0 U
b0 V
#106000
0)
0;
#106500
1)
b1101011 1
1;
b0 T
b0 U
b0 V
#107000
0)
0;
#107500
1)
b1101100 1
1;
b0 T
b0 U
b0 V
#108000
0)
0;
#108500
1)
b1101101 1
1;
b0 T
b0 U
b0 V
#109000
0)
0;
#109500
1)
b1101110 1
1;
b0 T
b0 U
b0 V
#110000
0)
0;
#110500
1)
b1101111 1
1;
b0 T
b0 U
b0 V
#111000
0)
0;
#111500
1)
b1110000 1
1;
b0 T
b0 U
b0 V
#112000
0)
0;
#112500
1)
b1110001 1
1;
b0 T
b0 U
b0 V
#113000
0)
0;
#113500
1)
b1110010 1
1;
b0 T
b0 U
b0 V
#114000
0)
0;
#114500
1)
b1110011 1
1;
b0 T
b0 U
b0 V
#115000
0)
0;
#115500
1)
b1110100 1
1;
b0 T
b0 U
b0 V
#116000
0)
0;
#116500
1)
b1110101 1
1;
b0 T
b0 U
b0 V
#117000
0)
0;
#117500
1)
b1110110 1
1;
b0 T
b0 U
b0 V
#118000
0)
0;
#118500
1)
b1110111 1
1;
b0 T
b0 U
b0 V
#119000
0)
0;
#119500
1)
b1111000 1
1;
b0 T
b0 U
b0 V
#120000
0)
0;
#120500
1)
b1111001 1
1;
b0 T
b0 U
b0 V
#121000
0)
0;
#121500
1)
b1111010 1
1;
b0 T
b0 U
b0 V
#122000
0)
0;
#122500
1)
b1111011 1
1;
b0 T
b0 U
b0 V
#123000
0)
0;
#123500
1)
b1111100 1
1;
b0 T
b0 U
b0 V
#124000
0)
0;
#124500
1)
b1111101 1
1;
b0 T
b0 U
b0 V
#125000
0)
0;
#125500
1)
b1111110 1
1;
b0 T
b0 U
b0 V
#126000
0)
0;
#126500
1)
b1111111 1
1;
b0 T
b0 U
b0 V
#127000
0)
0;
